{"sysstat": {
	"hosts": [
		{
			"nodename": "rtp-qs1-14-jade",
			"sysname": "Linux",
			"release": "5.18.11-200.NOCPPCFIE.fc36.aarch64",
			"machine": "aarch64",
			"number-of-cpus": 160,
			"file-date": "2023-07-11",
			"file-utc-time": "10:21:31",
			"timezone": "EST",
			"statistics": [
				{
					"timestamp": {"date": "2023-07-11", "time": "10:22:01", "utc": 1, "interval": 30},
					"cpu-load": [
						{"cpu": "all", "user": 54.09, "nice": 0.00, "system": 18.39, "iowait": 0.38, "steal": 0.00, "idle": 27.15},
						{"cpu": "0", "user": 48.05, "nice": 0.00, "system": 18.99, "iowait": 0.00, "steal": 0.00, "idle": 32.97},
						{"cpu": "1", "user": 52.96, "nice": 0.00, "system": 14.39, "iowait": 1.38, "steal": 0.00, "idle": 31.27},
						{"cpu": "2", "user": 48.93, "nice": 0.00, "system": 13.60, "iowait": 0.42, "steal": 0.00, "idle": 37.06},
						{"cpu": "3", "user": 46.09, "nice": 0.00, "system": 17.04, "iowait": 0.03, "steal": 0.00, "idle": 36.83},
						{"cpu": "4", "user": 59.99, "nice": 0.00, "system": 23.28, "iowait": 0.00, "steal": 0.00, "idle": 16.73},
						{"cpu": "5", "user": 52.39, "nice": 0.00, "system": 9.89, "iowait": 0.00, "steal": 0.00, "idle": 37.71},
						{"cpu": "6", "user": 58.46, "nice": 0.00, "system": 22.17, "iowait": 0.25, "steal": 0.00, "idle": 19.12},
						{"cpu": "7", "user": 62.60, "nice": 0.00, "system": 16.86, "iowait": 0.00, "steal": 0.00, "idle": 20.54},
						{"cpu": "8", "user": 50.12, "nice": 0.00, "system": 31.74, "iowait": 0.00, "steal": 0.00, "idle": 18.14},
						{"cpu": "9", "user": 54.02, "nice": 0.00, "system": 24.38, "iowait": 0.00, "steal": 0.00, "idle": 21.60},
						{"cpu": "10", "user": 51.97, "nice": 0.00, "system": 25.25, "iowait": 0.00, "steal": 0.00, "idle": 22.78},
						{"cpu": "11", "user": 57.72, "nice": 0.00, "system": 16.84, "iowait": 0.24, "steal": 0.00, "idle": 25.20},
						{"cpu": "12", "user": 48.35, "nice": 0.00, "system": 17.09, "iowait": 1.10, "steal": 0.00, "idle": 33.46},
						{"cpu": "13", "user": 51.32, "nice": 0.00, "system": 23.26, "iowait": 0.00, "steal": 0.00, "idle": 25.42},
						{"cpu": "14", "user": 56.69, "nice": 0.00, "system": 10.97, "iowait": 0.00, "steal": 0.00, "idle": 32.34},
						{"cpu": "15", "user": 50.75, "nice": 0.00, "system": 20.46, "iowait": 0.00, "steal": 0.00, "idle": 28.79},
						{"cpu": "16", "user": 57.98, "nice": 0.00, "system": 16.36, "iowait": 0.32, "steal": 0.00, "idle": 25.34},
						{"cpu": "17", "user": 52.63, "nice": 0.00, "system": 17.51, "iowait": 0.39, "steal": 0.00, "idle": 29.48},
						{"cpu": "18", "user": 55.50, "nice": 0.00, "system": 11.29, "iowait": 0.07, "steal": 0.00, "idle": 33.13},
						{"cpu": "19", "user": 52.51, "nice": 0.00, "system": 11.69, "iowait": 0.00, "steal": 0.00, "idle": 35.80},
						{"cpu": "20", "user": 49.60, "nice": 0.00, "system": 22.00, "iowait": 0.74, "steal": 0.00, "idle": 27.67},
						{"cpu": "21", "user": 50.56, "nice": 0.00, "system": 17.11, "iowait": 0.00, "steal": 0.00, "idle": 32.33},
						{"cpu": "22", "user": 52.16, "nice": 0.00, "system": 9.29, "iowait": 0.10, "steal": 0.00, "idle": 38.45},
						{"cpu": "23", "user": 42.58, "nice": 0.00, "system": 20.94, "iowait": 1.21, "steal": 0.00, "idle": 35.27},
						{"cpu": "24", "user": 56.94, "nice": 0.00, "system": 16.52, "iowait": 5.46, "steal": 0.00, "idle": 21.08},
						{"cpu": "25", "user": 56.67, "nice": 0.00, "system": 27.66, "iowait": 0.41, "steal": 0.00, "idle": 15.26},
						{"cpu": "26", "user": 58.70, "nice": 0.00, "system": 26.28, "iowait": 1.52, "steal": 0.00, "idle": 13.50},
						{"cpu": "27", "user": 57.69, "nice": 0.00, "system": 22.07, "iowait": 0.00, "steal": 0.00, "idle": 20.24},
						{"cpu": "28", "user": 63.09, "nice": 0.00, "system": 14.34, "iowait": 0.28, "steal": 0.00, "idle": 22.28},
						{"cpu": "29", "user": 59.32, "nice": 0.00, "system": 13.24, "iowait": 0.04, "steal": 0.00, "idle": 27.40},
						{"cpu": "30", "user": 43.56, "nice": 0.00, "system": 27.39, "iowait": 0.04, "steal": 0.00, "idle": 29.02},
						{"cpu": "31", "user": 59.78, "nice": 0.00, "system": 16.88, "iowait": 0.03, "steal": 0.00, "idle": 23.31},
						{"cpu": "32", "user": 66.64, "nice": 0.00, "system": 13.60, "iowait": 0.42, "steal": 0.00, "idle": 19.33},
						{"cpu": "33", "user": 51.53, "nice": 0.00, "system": 13.89, "iowait": 0.00, "steal": 0.00, "idle": 34.58},
						{"cpu": "34", "user": 62.98, "nice": 0.00, "system": 21.16, "iowait": 0.42, "steal": 0.00, "idle": 15.45},
						{"cpu": "35", "user": 51.30, "nice": 0.00, "system": 21.08, "iowait": 0.35, "steal": 0.00, "idle": 27.27},
						{"cpu": "36", "user": 51.56, "nice": 0.00, "system": 14.51, "iowait": 0.07, "steal": 0.00, "idle": 33.86},
						{"cpu": "37", "user": 48.39, "nice": 0.00, "system": 21.51, "iowait": 1.19, "steal": 0.00, "idle": 28.91},
						{"cpu": "38", "user": 49.81, "nice": 0.00, "system": 19.89, "iowait": 0.07, "steal": 0.00, "idle": 30.24},
						{"cpu": "39", "user": 59.69, "nice": 0.00, "system": 18.79, "iowait": 0.00, "steal": 0.00, "idle": 21.52},
						{"cpu": "40", "user": 56.25, "nice": 0.00, "system": 19.97, "iowait": 0.96, "steal": 0.00, "idle": 22.81},
						{"cpu": "41", "user": 43.15, "nice": 0.00, "system": 21.99, "iowait": 0.64, "steal": 0.00, "idle": 34.22},
						{"cpu": "42", "user": 48.65, "nice": 0.00, "system": 13.91, "iowait": 0.00, "steal": 0.00, "idle": 37.44},
						{"cpu": "43", "user": 51.36, "nice": 0.00, "system": 25.38, "iowait": 1.57, "steal": 0.00, "idle": 21.68},
						{"cpu": "44", "user": 53.58, "nice": 0.00, "system": 20.76, "iowait": 0.04, "steal": 0.00, "idle": 25.63},
						{"cpu": "45", "user": 58.61, "nice": 0.00, "system": 10.46, "iowait": 0.63, "steal": 0.00, "idle": 30.30},
						{"cpu": "46", "user": 50.96, "nice": 0.00, "system": 22.35, "iowait": 0.24, "steal": 0.00, "idle": 26.45},
						{"cpu": "47", "user": 55.89, "nice": 0.00, "system": 13.11, "iowait": 0.00, "steal": 0.00, "idle": 31.00},
						{"cpu": "48", "user": 46.06, "nice": 0.00, "system": 19.76, "iowait": 0.46, "steal": 0.00, "idle": 33.72},
						{"cpu": "49", "user": 60.32, "nice": 0.00, "system": 22.15, "iowait": 0.00, "steal": 0.00, "idle": 17.54},
						{"cpu": "50", "user": 58.35, "nice": 0.00, "system": 17.46, "iowait": 0.52, "steal": 0.00, "idle": 23.67},
						{"cpu": "51", "user": 47.78, "nice": 0.00, "system": 14.59, "iowait": 0.32, "steal": 0.00, "idle": 37.32},
						{"cpu": "52", "user": 50.49, "nice": 0.00, "system": 12.91, "iowait": 0.28, "steal": 0.00, "idle": 36.32},
						{"cpu": "53", "user": 59.18, "nice": 0.00, "system": 21.22, "iowait": 0.03, "steal": 0.00, "idle": 19.56},
						{"cpu": "54", "user": 57.73, "nice": 0.00, "system": 25.76, "iowait": 0.35, "steal": 0.00, "idle": 16.16},
						{"cpu": "55", "user": 62.57, "nice": 0.00, "system": 14.28, "iowait": 0.21, "steal": 0.00, "idle": 22.94},
						{"cpu": "56", "user": 59.65, "nice": 0.00, "system": 18.29, "iowait": 0.31, "steal": 0.00, "idle": 21.74},
						{"cpu": "57", "user": 55.87, "nice": 0.00, "system": 19.09, "iowait": 0.00, "steal": 0.00, "idle": 25.04},
						{"cpu": "58", "user": 59.96, "nice": 0.00, "system": 12.91, "iowait": 0.07, "steal": 0.00, "idle": 27.06},
						{"cpu": "59", "user": 54.30, "nice": 0.00, "system": 17.64, "iowait": 0.04, "steal": 0.00, "idle": 28.03},
						{"cpu": "60", "user": 51.09, "nice": 0.00, "system": 21.93, "iowait": 0.04, "steal": 0.00, "idle": 26.94},
						{"cpu": "61", "user": 55.80, "nice": 0.00, "system": 11.45, "iowait": 0.00, "steal": 0.00, "idle": 32.75},
						{"cpu": "62", "user": 52.15, "nice": 0.00, "system": 20.28, "iowait": 0.65, "steal": 0.00, "idle": 26.92},
						{"cpu": "63", "user": 49.93, "nice": 0.00, "system": 17.64, "iowait": 0.00, "steal": 0.00, "idle": 32.43}
					]
				},
				{
					"timestamp": {"date": "2023-07-11", "time": "10:22:31", "utc": 1, "interval": 30},
					"cpu-load": [
						{"cpu": "all", "user": 58.25, "nice": 0.00, "system": 20.49, "iowait": 0.26, "steal": 0.00, "idle": 21.00},
						{"cpu": "0", "user": 53.90, "nice": 0.00, "system": 22.62, "iowait": 0.10, "steal": 0.00, "idle": 23.38},
						{"cpu": "1", "user": 58.01, "nice": 0.00, "system": 14.90, "iowait": 0.07, "steal": 0.00, "idle": 27.02},
						{"cpu": "2", "user": 60.89, "nice": 0.00, "system": 11.11, "iowait": 0.00, "steal": 0.00, "idle": 28.00},
						{"cpu": "3", "user": 54.50, "nice": 0.00, "system": 21.84, "iowait": 0.00, "steal": 0.00, "idle": 23.66},
						{"cpu": "4", "user": 55.10, "nice": 0.00, "system": 22.10, "iowait": 0.25, "steal": 0.00, "idle": 22.56},
						{"cpu": "5", "user": 51.46, "nice": 0.00, "system": 26.95, "iowait": 1.99, "steal": 0.00, "idle": 19.59},
						{"cpu": "6", "user": 55.71, "nice": 0.00, "system": 20.21, "iowait": 0.00, "steal": 0.00, "idle": 24.08},
						{"cpu": "7", "user": 50.77, "nice": 0.00, "system": 29.03, "iowait": 0.62, "steal": 0.00, "idle": 19.58},
						{"cpu": "8", "user": 57.12, "nice": 0.00, "system": 17.81, "iowait": 0.00, "steal": 0.00, "idle": 25.07},
						{"cpu": "9", "user": 52.61, "nice": 0.00, "system": 24.89, "iowait": 0.00, "steal": 0.00, "idle": 22.50},
						{"cpu": "10", "user": 53.09, "nice": 0.00, "system": 23.30, "iowait": 0.00, "steal": 0.00, "idle": 23.62},
						{"cpu": "11", "user": 60.67, "nice": 0.00, "system": 12.93, "iowait": 0.00, "steal": 0.00, "idle": 26.39},
						{"cpu": "12", "user": 61.61, "nice": 0.00, "system": 11.34, "iowait": 0.00, "steal": 0.00, "idle": 27.05},
						{"cpu": "13", "user": 53.75, "nice": 0.00, "system": 22.38, "iowait": 0.07, "steal": 0.00, "idle": 23.80},
						{"cpu": "14", "user": 55.04, "nice": 0.00, "system": 23.18, "iowait": 1.54, "steal": 0.00, "idle": 20.23},
						{"cpu": "15", "user": 53.28, "nice": 0.00, "system": 23.13, "iowait": 0.03, "steal": 0.00, "idle": 23.55},
						{"cpu": "16", "user": 59.02, "nice": 0.00, "system": 18.68, "iowait": 0.11, "steal": 0.00, "idle": 22.19},
						{"cpu": "17", "user": 58.46, "nice": 0.00, "system": 16.81, "iowait": 0.00, "steal": 0.00, "idle": 24.73},
						{"cpu": "18", "user": 50.89, "nice": 0.00, "system": 32.34, "iowait": 4.11, "steal": 0.00, "idle": 12.66},
						{"cpu": "19", "user": 60.87, "nice": 0.00, "system": 14.57, "iowait": 0.45, "steal": 0.00, "idle": 24.10},
						{"cpu": "20", "user": 54.20, "nice": 0.00, "system": 25.42, "iowait": 0.00, "steal": 0.00, "idle": 20.37},
						{"cpu": "21", "user": 59.64, "nice": 0.00, "system": 19.43, "iowait": 0.00, "steal": 0.00, "idle": 20.92},
						{"cpu": "22", "user": 62.65, "nice": 0.00, "system": 12.70, "iowait": 0.46, "steal": 0.00, "idle": 24.20},
						{"cpu": "23", "user": 55.54, "nice": 0.00, "system": 23.63, "iowait": 0.00, "steal": 0.00, "idle": 20.83},
						{"cpu": "24", "user": 62.36, "nice": 0.00, "system": 13.53, "iowait": 0.00, "steal": 0.00, "idle": 24.10},
						{"cpu": "25", "user": 59.60, "nice": 0.00, "system": 18.13, "iowait": 0.00, "steal": 0.00, "idle": 22.27},
						{"cpu": "26", "user": 56.81, "nice": 0.00, "system": 23.26, "iowait": 0.52, "steal": 0.00, "idle": 19.41},
						{"cpu": "27", "user": 55.69, "nice": 0.00, "system": 24.16, "iowait": 0.00, "steal": 0.00, "idle": 20.16},
						{"cpu": "28", "user": 62.32, "nice": 0.00, "system": 13.37, "iowait": 0.00, "steal": 0.00, "idle": 24.32},
						{"cpu": "29", "user": 60.52, "nice": 0.00, "system": 14.85, "iowait": 0.21, "steal": 0.00, "idle": 24.41},
						{"cpu": "30", "user": 53.95, "nice": 0.00, "system": 25.50, "iowait": 0.00, "steal": 0.00, "idle": 20.55},
						{"cpu": "31", "user": 59.78, "nice": 0.00, "system": 18.35, "iowait": 0.00, "steal": 0.00, "idle": 21.87},
						{"cpu": "32", "user": 54.52, "nice": 0.00, "system": 30.84, "iowait": 1.51, "steal": 0.00, "idle": 13.14},
						{"cpu": "33", "user": 61.67, "nice": 0.00, "system": 18.21, "iowait": 0.18, "steal": 0.00, "idle": 19.94},
						{"cpu": "34", "user": 66.46, "nice": 0.00, "system": 11.71, "iowait": 0.00, "steal": 0.00, "idle": 21.84},
						{"cpu": "35", "user": 62.40, "nice": 0.00, "system": 18.43, "iowait": 0.00, "steal": 0.00, "idle": 19.17},
						{"cpu": "36", "user": 62.38, "nice": 0.00, "system": 17.59, "iowait": 0.00, "steal": 0.00, "idle": 20.03},
						{"cpu": "37", "user": 55.34, "nice": 0.00, "system": 25.41, "iowait": 0.00, "steal": 0.00, "idle": 19.26},
						{"cpu": "38", "user": 61.03, "nice": 0.00, "system": 21.20, "iowait": 0.00, "steal": 0.00, "idle": 17.77},
						{"cpu": "39", "user": 60.52, "nice": 0.00, "system": 19.86, "iowait": 0.00, "steal": 0.00, "idle": 19.62},
						{"cpu": "40", "user": 59.23, "nice": 0.00, "system": 23.40, "iowait": 0.18, "steal": 0.00, "idle": 17.19},
						{"cpu": "41", "user": 61.56, "nice": 0.00, "system": 20.14, "iowait": 0.00, "steal": 0.00, "idle": 18.29},
						{"cpu": "42", "user": 61.93, "nice": 0.00, "system": 19.42, "iowait": 0.00, "steal": 0.00, "idle": 18.64},
						{"cpu": "43", "user": 58.28, "nice": 0.00, "system": 20.42, "iowait": 0.74, "steal": 0.00, "idle": 20.56},
						{"cpu": "44", "user": 57.93, "nice": 0.00, "system": 22.75, "iowait": 0.32, "steal": 0.00, "idle": 19.00},
						{"cpu": "45", "user": 67.39, "nice": 0.00, "system": 13.02, "iowait": 0.00, "steal": 0.00, "idle": 19.59},
						{"cpu": "46", "user": 57.51, "nice": 0.00, "system": 23.84, "iowait": 0.00, "steal": 0.00, "idle": 18.65},
						{"cpu": "47", "user": 64.29, "nice": 0.00, "system": 16.45, "iowait": 0.89, "steal": 0.00, "idle": 18.37},
						{"cpu": "48", "user": 55.14, "nice": 0.00, "system": 25.27, "iowait": 0.00, "steal": 0.00, "idle": 19.59},
						{"cpu": "49", "user": 55.86, "nice": 0.00, "system": 24.68, "iowait": 0.00, "steal": 0.00, "idle": 19.45},
						{"cpu": "50", "user": 59.84, "nice": 0.00, "system": 19.11, "iowait": 0.00, "steal": 0.00, "idle": 21.05},
						{"cpu": "51", "user": 58.12, "nice": 0.00, "system": 21.65, "iowait": 0.75, "steal": 0.00, "idle": 19.48},
						{"cpu": "52", "user": 62.38, "nice": 0.00, "system": 17.31, "iowait": 0.00, "steal": 0.00, "idle": 20.31},
						{"cpu": "53", "user": 53.75, "nice": 0.00, "system": 27.45, "iowait": 0.00, "steal": 0.00, "idle": 18.79},
						{"cpu": "54", "user": 54.25, "nice": 0.00, "system": 26.79, "iowait": 0.29, "steal": 0.00, "idle": 18.67},
						{"cpu": "55", "user": 63.81, "nice": 0.00, "system": 15.99, "iowait": 0.00, "steal": 0.00, "idle": 20.20},
						{"cpu": "56", "user": 60.17, "nice": 0.00, "system": 18.85, "iowait": 0.00, "steal": 0.00, "idle": 20.98},
						{"cpu": "57", "user": 56.00, "nice": 0.00, "system": 23.56, "iowait": 0.00, "steal": 0.00, "idle": 20.44},
						{"cpu": "58", "user": 61.05, "nice": 0.00, "system": 17.72, "iowait": 0.00, "steal": 0.00, "idle": 21.23},
						{"cpu": "59", "user": 58.58, "nice": 0.00, "system": 20.41, "iowait": 0.00, "steal": 0.00, "idle": 21.02},
						{"cpu": "60", "user": 56.64, "nice": 0.00, "system": 23.92, "iowait": 0.00, "steal": 0.00, "idle": 19.45},
						{"cpu": "61", "user": 58.53, "nice": 0.00, "system": 24.04, "iowait": 0.76, "steal": 0.00, "idle": 16.67},
						{"cpu": "62", "user": 66.12, "nice": 0.00, "system": 14.74, "iowait": 0.00, "steal": 0.00, "idle": 19.14},
						{"cpu": "63", "user": 56.07, "nice": 0.00, "system": 24.27, "iowait": 0.00, "steal": 0.00, "idle": 19.66}
					]
				},
				{
					"timestamp": {"date": "2023-07-11", "time": "10:23:01", "utc": 1, "interval": 30},
					"cpu-load": [
						{"cpu": "all", "user": 58.45, "nice": 0.00, "system": 20.05, "iowait": 0.17, "steal": 0.00, "idle": 21.33},
						{"cpu": "0", "user": 54.32, "nice": 0.00, "system": 22.56, "iowait": 0.00, "steal": 0.00, "idle": 23.12},
						{"cpu": "1", "user": 57.34, "nice": 0.00, "system": 16.49, "iowait": 0.95, "steal": 0.00, "idle": 25.21},
						{"cpu": "2", "user": 52.80, "nice": 0.00, "system": 27.71, "iowait": 0.52, "steal": 0.00, "idle": 18.98},
						{"cpu": "3", "user": 54.52, "nice": 0.00, "system": 22.51, "iowait": 0.00, "steal": 0.00, "idle": 22.97},
						{"cpu": "4", "user": 53.07, "nice": 0.00, "system": 24.54, "iowait": 0.00, "steal": 0.00, "idle": 22.39},
						{"cpu": "5", "user": 60.24, "nice": 0.00, "system": 15.66, "iowait": 0.53, "steal": 0.00, "idle": 23.56},
						{"cpu": "6", "user": 55.73, "nice": 0.00, "system": 19.84, "iowait": 0.00, "steal": 0.00, "idle": 24.43},
						{"cpu": "7", "user": 58.46, "nice": 0.00, "system": 16.88, "iowait": 0.04, "steal": 0.00, "idle": 24.63},
						{"cpu": "8", "user": 56.00, "nice": 0.00, "system": 21.30, "iowait": 0.00, "steal": 0.00, "idle": 22.70},
						{"cpu": "9", "user": 53.42, "nice": 0.00, "system": 25.21, "iowait": 0.00, "steal": 0.00, "idle": 21.37},
						{"cpu": "10", "user": 52.67, "nice": 0.00, "system": 25.22, "iowait": 0.78, "steal": 0.00, "idle": 21.34},
						{"cpu": "11", "user": 61.55, "nice": 0.00, "system": 12.27, "iowait": 0.00, "steal": 0.00, "idle": 26.19},
						{"cpu": "12", "user": 56.81, "nice": 0.00, "system": 19.19, "iowait": 0.00, "steal": 0.00, "idle": 24.00},
						{"cpu": "13", "user": 55.39, "nice": 0.00, "system": 21.33, "iowait": 0.00, "steal": 0.00, "idle": 23.28},
						{"cpu": "14", "user": 58.75, "nice": 0.00, "system": 17.04, "iowait": 1.22, "steal": 0.00, "idle": 23.00},
						{"cpu": "15", "user": 54.88, "nice": 0.00, "system": 21.90, "iowait": 0.00, "steal": 0.00, "idle": 23.22},
						{"cpu": "16", "user": 61.46, "nice": 0.00, "system": 16.58, "iowait": 0.00, "steal": 0.00, "idle": 21.96},
						{"cpu": "17", "user": 57.86, "nice": 0.00, "system": 18.88, "iowait": 0.00, "steal": 0.00, "idle": 23.26},
						{"cpu": "18", "user": 54.47, "nice": 0.00, "system": 25.65, "iowait": 0.95, "steal": 0.00, "idle": 18.93},
						{"cpu": "19", "user": 57.14, "nice": 0.00, "system": 21.45, "iowait": 0.56, "steal": 0.00, "idle": 20.86},
						{"cpu": "20", "user": 53.83, "nice": 0.00, "system": 25.99, "iowait": 0.00, "steal": 0.00, "idle": 20.18},
						{"cpu": "21", "user": 55.78, "nice": 0.00, "system": 24.86, "iowait": 0.00, "steal": 0.00, "idle": 19.36},
						{"cpu": "22", "user": 62.73, "nice": 0.00, "system": 13.59, "iowait": 0.94, "steal": 0.00, "idle": 22.74},
						{"cpu": "23", "user": 53.83, "nice": 0.00, "system": 24.43, "iowait": 0.00, "steal": 0.00, "idle": 21.74},
						{"cpu": "24", "user": 62.60, "nice": 0.00, "system": 14.79, "iowait": 0.00, "steal": 0.00, "idle": 22.61},
						{"cpu": "25", "user": 59.03, "nice": 0.00, "system": 18.63, "iowait": 0.00, "steal": 0.00, "idle": 22.34},
						{"cpu": "26", "user": 57.31, "nice": 0.00, "system": 20.96, "iowait": 0.00, "steal": 0.00, "idle": 21.73},
						{"cpu": "27", "user": 55.92, "nice": 0.00, "system": 23.70, "iowait": 0.00, "steal": 0.00, "idle": 20.39},
						{"cpu": "28", "user": 61.62, "nice": 0.00, "system": 13.51, "iowait": 0.00, "steal": 0.00, "idle": 24.87},
						{"cpu": "29", "user": 61.62, "nice": 0.00, "system": 13.62, "iowait": 0.07, "steal": 0.00, "idle": 24.69},
						{"cpu": "30", "user": 54.87, "nice": 0.00, "system": 24.47, "iowait": 0.00, "steal": 0.00, "idle": 20.66},
						{"cpu": "31", "user": 61.19, "nice": 0.00, "system": 17.68, "iowait": 0.00, "steal": 0.00, "idle": 21.12},
						{"cpu": "32", "user": 57.27, "nice": 0.00, "system": 20.82, "iowait": 0.00, "steal": 0.00, "idle": 21.91},
						{"cpu": "33", "user": 63.57, "nice": 0.00, "system": 13.84, "iowait": 0.00, "steal": 0.00, "idle": 22.59},
						{"cpu": "34", "user": 62.56, "nice": 0.00, "system": 17.07, "iowait": 0.49, "steal": 0.00, "idle": 19.88},
						{"cpu": "35", "user": 60.01, "nice": 0.00, "system": 17.74, "iowait": 0.00, "steal": 0.00, "idle": 22.24},
						{"cpu": "36", "user": 59.95, "nice": 0.00, "system": 19.23, "iowait": 0.92, "steal": 0.00, "idle": 19.90},
						{"cpu": "37", "user": 53.27, "nice": 0.00, "system": 24.50, "iowait": 0.00, "steal": 0.00, "idle": 22.23},
						{"cpu": "38", "user": 58.22, "nice": 0.00, "system": 20.59, "iowait": 0.00, "steal": 0.00, "idle": 21.19},
						{"cpu": "39", "user": 57.83, "nice": 0.00, "system": 19.25, "iowait": 0.00, "steal": 0.00, "idle": 22.92},
						{"cpu": "40", "user": 57.21, "nice": 0.00, "system": 21.25, "iowait": 0.00, "steal": 0.00, "idle": 21.54},
						{"cpu": "41", "user": 60.40, "nice": 0.00, "system": 18.82, "iowait": 0.00, "steal": 0.00, "idle": 20.77},
						{"cpu": "42", "user": 56.54, "nice": 0.00, "system": 20.07, "iowait": 0.57, "steal": 0.00, "idle": 22.83},
						{"cpu": "43", "user": 56.93, "nice": 0.00, "system": 20.75, "iowait": 0.00, "steal": 0.00, "idle": 22.32},
						{"cpu": "44", "user": 56.25, "nice": 0.00, "system": 22.58, "iowait": 0.00, "steal": 0.00, "idle": 21.17},
						{"cpu": "45", "user": 57.00, "nice": 0.00, "system": 21.84, "iowait": 0.32, "steal": 0.00, "idle": 20.85},
						{"cpu": "46", "user": 54.50, "nice": 0.00, "system": 23.66, "iowait": 0.00, "steal": 0.00, "idle": 21.84},
						{"cpu": "47", "user": 62.59, "nice": 0.00, "system": 13.75, "iowait": 0.00, "steal": 0.00, "idle": 23.66},
						{"cpu": "48", "user": 59.51, "nice": 0.00, "system": 21.97, "iowait": 0.00, "steal": 0.00, "idle": 18.52},
						{"cpu": "49", "user": 60.02, "nice": 0.00, "system": 20.83, "iowait": 0.00, "steal": 0.00, "idle": 19.15},
						{"cpu": "50", "user": 65.22, "nice": 0.00, "system": 14.53, "iowait": 0.00, "steal": 0.00, "idle": 20.25},
						{"cpu": "51", "user": 59.47, "nice": 0.00, "system": 20.81, "iowait": 0.21, "steal": 0.00, "idle": 19.50},
						{"cpu": "52", "user": 65.38, "nice": 0.00, "system": 13.79, "iowait": 0.39, "steal": 0.00, "idle": 20.44},
						{"cpu": "53", "user": 56.15, "nice": 0.00, "system": 24.79, "iowait": 0.00, "steal": 0.00, "idle": 19.05},
						{"cpu": "54", "user": 57.69, "nice": 0.00, "system": 24.87, "iowait": 0.00, "steal": 0.00, "idle": 17.44},
						{"cpu": "55", "user": 54.04, "nice": 0.00, "system": 31.53, "iowait": 1.31, "steal": 0.00, "idle": 13.12},
						{"cpu": "56", "user": 62.95, "nice": 0.00, "system": 19.90, "iowait": 0.00, "steal": 0.00, "idle": 17.15},
						{"cpu": "57", "user": 60.14, "nice": 0.00, "system": 21.71, "iowait": 0.00, "steal": 0.00, "idle": 18.15},
						{"cpu": "58", "user": 68.29, "nice": 0.00, "system": 12.24, "iowait": 0.00, "steal": 0.00, "idle": 19.47},
						{"cpu": "59", "user": 60.52, "nice": 0.00, "system": 20.15, "iowait": 0.04, "steal": 0.00, "idle": 19.29},
						{"cpu": "60", "user": 58.57, "nice": 0.00, "system": 22.81, "iowait": 0.00, "steal": 0.00, "idle": 18.62},
						{"cpu": "61", "user": 65.53, "nice": 0.00, "system": 14.44, "iowait": 0.00, "steal": 0.00, "idle": 20.03},
						{"cpu": "62", "user": 67.49, "nice": 0.00, "system": 12.09, "iowait": 0.00, "steal": 0.00, "idle": 20.43},
						{"cpu": "63", "user": 59.40, "nice": 0.00, "system": 22.14, "iowait": 0.07, "steal": 0.00, "idle": 18.40}
					]
				},
				{
					"timestamp": {"date": "2023-07-11", "time": "10:23:31", "utc": 1, "interval": 30},
					"cpu-load": [
						{"cpu": "all", "user": 58.99, "nice": 0.00, "system": 20.37, "iowait": 0.16, "steal": 0.00, "idle": 20.48},
						{"cpu": "0", "user": 53.90, "nice": 0.00, "system": 24.33, "iowait": 0.00, "steal": 0.00, "idle": 21.77},
						{"cpu": "1", "user": 61.08, "nice": 0.00, "system": 15.15, "iowait": 0.00, "steal": 0.00, "idle": 23.76},
						{"cpu": "2", "user": 58.12, "nice": 0.00, "system": 20.64, "iowait": 1.29, "steal": 0.00, "idle": 19.94},
						{"cpu": "3", "user": 54.62, "nice": 0.00, "system": 23.39, "iowait": 0.00, "steal": 0.00, "idle": 22.00},
						{"cpu": "4", "user": 52.87, "nice": 0.00, "system": 24.85, "iowait": 0.04, "steal": 0.00, "idle": 22.25},
						{"cpu": "5", "user": 58.74, "nice": 0.00, "system": 17.69, "iowait": 0.88, "steal": 0.00, "idle": 22.69},
						{"cpu": "6", "user": 55.37, "nice": 0.00, "system": 21.22, "iowait": 0.00, "steal": 0.00, "idle": 23.41},
						{"cpu": "7", "user": 58.40, "nice": 0.00, "system": 20.92, "iowait": 1.53, "steal": 0.00, "idle": 19.15},
						{"cpu": "8", "user": 56.28, "nice": 0.00, "system": 20.09, "iowait": 0.00, "steal": 0.00, "idle": 23.63},
						{"cpu": "9", "user": 52.65, "nice": 0.00, "system": 26.65, "iowait": 0.00, "steal": 0.00, "idle": 20.70},
						{"cpu": "10", "user": 53.67, "nice": 0.00, "system": 24.75, "iowait": 0.00, "steal": 0.00, "idle": 21.57},
						{"cpu": "11", "user": 59.97, "nice": 0.00, "system": 15.95, "iowait": 0.04, "steal": 0.00, "idle": 24.05},
						{"cpu": "12", "user": 59.97, "nice": 0.00, "system": 20.08, "iowait": 0.00, "steal": 0.00, "idle": 19.94},
						{"cpu": "13", "user": 54.97, "nice": 0.00, "system": 22.77, "iowait": 0.00, "steal": 0.00, "idle": 22.27},
						{"cpu": "14", "user": 61.94, "nice": 0.00, "system": 13.90, "iowait": 0.35, "steal": 0.00, "idle": 23.81},
						{"cpu": "15", "user": 55.39, "nice": 0.00, "system": 22.30, "iowait": 0.25, "steal": 0.00, "idle": 22.06},
						{"cpu": "16", "user": 60.67, "nice": 0.00, "system": 18.46, "iowait": 0.00, "steal": 0.00, "idle": 20.87},
						{"cpu": "17", "user": 60.77, "nice": 0.00, "system": 17.62, "iowait": 0.00, "steal": 0.00, "idle": 21.61},
						{"cpu": "18", "user": 67.41, "nice": 0.00, "system": 13.06, "iowait": 0.18, "steal": 0.00, "idle": 19.36},
						{"cpu": "19", "user": 62.75, "nice": 0.00, "system": 15.22, "iowait": 0.00, "steal": 0.00, "idle": 22.03},
						{"cpu": "20", "user": 56.06, "nice": 0.00, "system": 24.50, "iowait": 0.00, "steal": 0.00, "idle": 19.43},
						{"cpu": "21", "user": 57.54, "nice": 0.00, "system": 22.32, "iowait": 0.00, "steal": 0.00, "idle": 20.14},
						{"cpu": "22", "user": 59.27, "nice": 0.00, "system": 20.93, "iowait": 0.00, "steal": 0.00, "idle": 19.79},
						{"cpu": "23", "user": 52.05, "nice": 0.00, "system": 30.50, "iowait": 1.54, "steal": 0.00, "idle": 15.91},
						{"cpu": "24", "user": 60.02, "nice": 0.00, "system": 23.21, "iowait": 0.49, "steal": 0.00, "idle": 16.28},
						{"cpu": "25", "user": 61.35, "nice": 0.00, "system": 20.46, "iowait": 0.00, "steal": 0.00, "idle": 18.19},
						{"cpu": "26", "user": 64.09, "nice": 0.00, "system": 13.62, "iowait": 0.00, "steal": 0.00, "idle": 22.29},
						{"cpu": "27", "user": 55.83, "nice": 0.00, "system": 25.32, "iowait": 0.00, "steal": 0.00, "idle": 18.84},
						{"cpu": "28", "user": 62.11, "nice": 0.00, "system": 15.32, "iowait": 0.00, "steal": 0.00, "idle": 22.57},
						{"cpu": "29", "user": 61.50, "nice": 0.00, "system": 16.35, "iowait": 0.00, "steal": 0.00, "idle": 22.15},
						{"cpu": "30", "user": 52.68, "nice": 0.00, "system": 29.33, "iowait": 0.00, "steal": 0.00, "idle": 17.99},
						{"cpu": "31", "user": 61.02, "nice": 0.00, "system": 19.26, "iowait": 0.00, "steal": 0.00, "idle": 19.72},
						{"cpu": "32", "user": 57.44, "nice": 0.00, "system": 21.90, "iowait": 0.71, "steal": 0.00, "idle": 19.95},
						{"cpu": "33", "user": 63.13, "nice": 0.00, "system": 13.62, "iowait": 0.00, "steal": 0.00, "idle": 23.25},
						{"cpu": "34", "user": 56.73, "nice": 0.00, "system": 25.32, "iowait": 0.61, "steal": 0.00, "idle": 17.34},
						{"cpu": "35", "user": 61.84, "nice": 0.00, "system": 18.31, "iowait": 0.00, "steal": 0.00, "idle": 19.85},
						{"cpu": "36", "user": 62.85, "nice": 0.00, "system": 14.87, "iowait": 0.00, "steal": 0.00, "idle": 22.28},
						{"cpu": "37", "user": 54.94, "nice": 0.00, "system": 24.86, "iowait": 0.00, "steal": 0.00, "idle": 20.20},
						{"cpu": "38", "user": 58.67, "nice": 0.00, "system": 21.08, "iowait": 0.00, "steal": 0.00, "idle": 20.25},
						{"cpu": "39", "user": 58.84, "nice": 0.00, "system": 20.53, "iowait": 0.00, "steal": 0.00, "idle": 20.64},
						{"cpu": "40", "user": 59.26, "nice": 0.00, "system": 20.04, "iowait": 0.04, "steal": 0.00, "idle": 20.67},
						{"cpu": "41", "user": 55.41, "nice": 0.00, "system": 23.40, "iowait": 0.00, "steal": 0.00, "idle": 21.18},
						{"cpu": "42", "user": 56.38, "nice": 0.00, "system": 23.92, "iowait": 0.04, "steal": 0.00, "idle": 19.66},
						{"cpu": "43", "user": 58.59, "nice": 0.00, "system": 20.65, "iowait": 0.00, "steal": 0.00, "idle": 20.76},
						{"cpu": "44", "user": 55.24, "nice": 0.00, "system": 24.55, "iowait": 0.00, "steal": 0.00, "idle": 20.21},
						{"cpu": "45", "user": 61.19, "nice": 0.00, "system": 13.99, "iowait": 0.28, "steal": 0.00, "idle": 24.54},
						{"cpu": "46", "user": 55.36, "nice": 0.00, "system": 24.56, "iowait": 0.00, "steal": 0.00, "idle": 20.09},
						{"cpu": "47", "user": 64.30, "nice": 0.00, "system": 14.55, "iowait": 0.00, "steal": 0.00, "idle": 21.16},
						{"cpu": "48", "user": 58.23, "nice": 0.00, "system": 22.70, "iowait": 0.00, "steal": 0.00, "idle": 19.07},
						{"cpu": "49", "user": 59.41, "nice": 0.00, "system": 20.93, "iowait": 0.00, "steal": 0.00, "idle": 19.66},
						{"cpu": "50", "user": 64.40, "nice": 0.00, "system": 13.93, "iowait": 0.21, "steal": 0.00, "idle": 21.46},
						{"cpu": "51", "user": 61.07, "nice": 0.00, "system": 18.43, "iowait": 0.31, "steal": 0.00, "idle": 20.18},
						{"cpu": "52", "user": 64.13, "nice": 0.00, "system": 15.03, "iowait": 0.00, "steal": 0.00, "idle": 20.84},
						{"cpu": "53", "user": 57.53, "nice": 0.00, "system": 24.96, "iowait": 0.00, "steal": 0.00, "idle": 17.51},
						{"cpu": "54", "user": 55.92, "nice": 0.00, "system": 25.89, "iowait": 0.00, "steal": 0.00, "idle": 18.19},
						{"cpu": "55", "user": 64.52, "nice": 0.00, "system": 15.62, "iowait": 0.00, "steal": 0.00, "idle": 19.86},
						{"cpu": "56", "user": 67.22, "nice": 0.00, "system": 14.78, "iowait": 0.84, "steal": 0.00, "idle": 17.16},
						{"cpu": "57", "user": 56.19, "nice": 0.00, "system": 24.82, "iowait": 0.00, "steal": 0.00, "idle": 18.99},
						{"cpu": "58", "user": 66.86, "nice": 0.00, "system": 11.28, "iowait": 0.00, "steal": 0.00, "idle": 21.86},
						{"cpu": "59", "user": 55.89, "nice": 0.00, "system": 26.24, "iowait": 0.14, "steal": 0.00, "idle": 17.73},
						{"cpu": "60", "user": 58.52, "nice": 0.00, "system": 23.68, "iowait": 0.00, "steal": 0.00, "idle": 17.80},
						{"cpu": "61", "user": 65.40, "nice": 0.00, "system": 12.30, "iowait": 0.00, "steal": 0.00, "idle": 22.30},
						{"cpu": "62", "user": 57.18, "nice": 0.00, "system": 23.72, "iowait": 0.49, "steal": 0.00, "idle": 18.62},
						{"cpu": "63", "user": 59.19, "nice": 0.00, "system": 23.17, "iowait": 0.04, "steal": 0.00, "idle": 17.60}
					]
				},
				{
					"timestamp": {"date": "2023-07-11", "time": "10:24:01", "utc": 1, "interval": 30},
					"cpu-load": [
						{"cpu": "all", "user": 58.01, "nice": 0.00, "system": 20.50, "iowait": 0.20, "steal": 0.00, "idle": 21.30},
						{"cpu": "0", "user": 55.53, "nice": 0.00, "system": 23.39, "iowait": 0.00, "steal": 0.00, "idle": 21.07},
						{"cpu": "1", "user": 60.20, "nice": 0.00, "system": 18.28, "iowait": 0.00, "steal": 0.00, "idle": 21.52},
						{"cpu": "2", "user": 58.52, "nice": 0.00, "system": 24.29, "iowait": 0.66, "steal": 0.00, "idle": 16.52},
						{"cpu": "3", "user": 56.70, "nice": 0.00, "system": 22.78, "iowait": 0.00, "steal": 0.00, "idle": 20.53},
						{"cpu": "4", "user": 53.84, "nice": 0.00, "system": 25.66, "iowait": 0.00, "steal": 0.00, "idle": 20.50},
						{"cpu": "5", "user": 61.42, "nice": 0.00, "system": 15.48, "iowait": 0.32, "steal": 0.00, "idle": 22.77},
						{"cpu": "6", "user": 56.88, "nice": 0.00, "system": 22.32, "iowait": 0.00, "steal": 0.00, "idle": 20.80},
						{"cpu": "7", "user": 60.48, "nice": 0.00, "system": 20.22, "iowait": 0.67, "steal": 0.00, "idle": 18.64},
						{"cpu": "8", "user": 58.14, "nice": 0.00, "system": 23.58, "iowait": 0.17, "steal": 0.00, "idle": 18.10},
						{"cpu": "9", "user": 53.67, "nice": 0.00, "system": 27.10, "iowait": 0.00, "steal": 0.00, "idle": 19.23},
						{"cpu": "10", "user": 51.95, "nice": 0.00, "system": 28.61, "iowait": 0.00, "steal": 0.00, "idle": 19.44},
						{"cpu": "11", "user": 59.70, "nice": 0.00, "system": 19.75, "iowait": 0.00, "steal": 0.00, "idle": 20.55},
						{"cpu": "12", "user": 62.40, "nice": 0.00, "system": 14.35, "iowait": 0.00, "steal": 0.00, "idle": 23.25},
						{"cpu": "13", "user": 55.04, "nice": 0.00, "system": 24.42, "iowait": 0.00, "steal": 0.00, "idle": 20.53},
						{"cpu": "14", "user": 61.53, "nice": 0.00, "system": 15.34, "iowait": 0.03, "steal": 0.00, "idle": 23.10},
						{"cpu": "15", "user": 55.71, "nice": 0.00, "system": 24.25, "iowait": 0.00, "steal": 0.00, "idle": 20.04},
						{"cpu": "16", "user": 59.06, "nice": 0.00, "system": 17.98, "iowait": 1.13, "steal": 0.00, "idle": 21.83},
						{"cpu": "17", "user": 56.30, "nice": 0.00, "system": 23.46, "iowait": 0.24, "steal": 0.00, "idle": 20.00},
						{"cpu": "18", "user": 60.96, "nice": 0.00, "system": 15.48, "iowait": 0.18, "steal": 0.00, "idle": 23.39},
						{"cpu": "19", "user": 60.28, "nice": 0.00, "system": 15.40, "iowait": 0.00, "steal": 0.00, "idle": 24.32},
						{"cpu": "20", "user": 52.11, "nice": 0.00, "system": 26.92, "iowait": 0.00, "steal": 0.00, "idle": 20.97},
						{"cpu": "21", "user": 56.52, "nice": 0.00, "system": 20.41, "iowait": 0.00, "steal": 0.00, "idle": 23.07},
						{"cpu": "22", "user": 52.47, "nice": 0.00, "system": 27.92, "iowait": 1.32, "steal": 0.00, "idle": 18.30},
						{"cpu": "23", "user": 56.33, "nice": 0.00, "system": 22.29, "iowait": 1.31, "steal": 0.00, "idle": 20.07},
						{"cpu": "24", "user": 59.33, "nice": 0.00, "system": 15.19, "iowait": 1.30, "steal": 0.00, "idle": 24.19},
						{"cpu": "25", "user": 56.21, "nice": 0.00, "system": 21.05, "iowait": 0.00, "steal": 0.00, "idle": 22.74},
						{"cpu": "26", "user": 62.68, "nice": 0.00, "system": 12.23, "iowait": 0.00, "steal": 0.00, "idle": 25.09},
						{"cpu": "27", "user": 51.81, "nice": 0.00, "system": 28.51, "iowait": 0.76, "steal": 0.00, "idle": 18.92},
						{"cpu": "28", "user": 60.44, "nice": 0.00, "system": 14.64, "iowait": 0.00, "steal": 0.00, "idle": 24.92},
						{"cpu": "29", "user": 61.55, "nice": 0.00, "system": 13.83, "iowait": 0.00, "steal": 0.00, "idle": 24.62},
						{"cpu": "30", "user": 54.12, "nice": 0.00, "system": 24.75, "iowait": 0.00, "steal": 0.00, "idle": 21.14},
						{"cpu": "31", "user": 57.66, "nice": 0.00, "system": 19.40, "iowait": 0.00, "steal": 0.00, "idle": 22.94},
						{"cpu": "32", "user": 57.24, "nice": 0.00, "system": 24.32, "iowait": 1.39, "steal": 0.00, "idle": 17.05},
						{"cpu": "33", "user": 62.24, "nice": 0.00, "system": 14.58, "iowait": 0.28, "steal": 0.00, "idle": 22.89},
						{"cpu": "34", "user": 60.60, "nice": 0.00, "system": 15.92, "iowait": 0.00, "steal": 0.00, "idle": 23.48},
						{"cpu": "35", "user": 59.61, "nice": 0.00, "system": 18.12, "iowait": 0.00, "steal": 0.00, "idle": 22.27},
						{"cpu": "36", "user": 63.08, "nice": 0.00, "system": 13.30, "iowait": 0.00, "steal": 0.00, "idle": 23.62},
						{"cpu": "37", "user": 55.51, "nice": 0.00, "system": 24.32, "iowait": 0.00, "steal": 0.00, "idle": 20.17},
						{"cpu": "38", "user": 56.33, "nice": 0.00, "system": 22.07, "iowait": 0.28, "steal": 0.00, "idle": 21.32},
						{"cpu": "39", "user": 56.11, "nice": 0.00, "system": 21.45, "iowait": 0.00, "steal": 0.00, "idle": 22.44},
						{"cpu": "40", "user": 57.21, "nice": 0.00, "system": 20.66, "iowait": 0.00, "steal": 0.00, "idle": 22.14},
						{"cpu": "41", "user": 56.94, "nice": 0.00, "system": 21.80, "iowait": 0.07, "steal": 0.00, "idle": 21.20},
						{"cpu": "42", "user": 58.72, "nice": 0.00, "system": 18.06, "iowait": 0.22, "steal": 0.00, "idle": 23.00},
						{"cpu": "43", "user": 58.81, "nice": 0.00, "system": 18.54, "iowait": 0.00, "steal": 0.00, "idle": 22.66},
						{"cpu": "44", "user": 54.99, "nice": 0.00, "system": 23.86, "iowait": 0.00, "steal": 0.00, "idle": 21.14},
						{"cpu": "45", "user": 62.37, "nice": 0.00, "system": 11.74, "iowait": 0.00, "steal": 0.00, "idle": 25.90},
						{"cpu": "46", "user": 47.47, "nice": 0.00, "system": 36.63, "iowait": 0.00, "steal": 0.00, "idle": 15.90},
						{"cpu": "47", "user": 61.01, "nice": 0.00, "system": 15.29, "iowait": 0.00, "steal": 0.00, "idle": 23.70},
						{"cpu": "48", "user": 56.16, "nice": 0.00, "system": 25.20, "iowait": 0.21, "steal": 0.00, "idle": 18.43},
						{"cpu": "49", "user": 58.52, "nice": 0.00, "system": 21.35, "iowait": 0.00, "steal": 0.00, "idle": 20.13},
						{"cpu": "50", "user": 62.03, "nice": 0.00, "system": 14.62, "iowait": 0.00, "steal": 0.00, "idle": 23.36},
						{"cpu": "51", "user": 61.08, "nice": 0.00, "system": 19.71, "iowait": 0.00, "steal": 0.00, "idle": 19.21},
						{"cpu": "52", "user": 62.78, "nice": 0.00, "system": 13.99, "iowait": 0.04, "steal": 0.00, "idle": 23.20},
						{"cpu": "53", "user": 54.89, "nice": 0.00, "system": 24.20, "iowait": 0.00, "steal": 0.00, "idle": 20.91},
						{"cpu": "54", "user": 53.45, "nice": 0.00, "system": 27.14, "iowait": 0.00, "steal": 0.00, "idle": 19.41},
						{"cpu": "55", "user": 62.24, "nice": 0.00, "system": 16.73, "iowait": 0.35, "steal": 0.00, "idle": 20.68},
						{"cpu": "56", "user": 64.91, "nice": 0.00, "system": 12.93, "iowait": 0.25, "steal": 0.00, "idle": 21.91},
						{"cpu": "57", "user": 58.06, "nice": 0.00, "system": 20.95, "iowait": 0.18, "steal": 0.00, "idle": 20.81},
						{"cpu": "58", "user": 61.18, "nice": 0.00, "system": 16.70, "iowait": 0.00, "steal": 0.00, "idle": 22.12},
						{"cpu": "59", "user": 55.68, "nice": 0.00, "system": 24.98, "iowait": 0.25, "steal": 0.00, "idle": 19.09},
						{"cpu": "60", "user": 56.77, "nice": 0.00, "system": 23.38, "iowait": 0.18, "steal": 0.00, "idle": 19.67},
						{"cpu": "61", "user": 61.88, "nice": 0.00, "system": 15.62, "iowait": 0.00, "steal": 0.00, "idle": 22.51},
						{"cpu": "62", "user": 60.50, "nice": 0.00, "system": 16.94, "iowait": 0.00, "steal": 0.00, "idle": 22.56},
						{"cpu": "63", "user": 54.49, "nice": 0.00, "system": 27.16, "iowait": 1.04, "steal": 0.00, "idle": 17.32}
					]
				},
				{
					"timestamp": {"date": "2023-07-11", "time": "10:24:31", "utc": 1, "interval": 30},
					"cpu-load": [
						{"cpu": "all", "user": 57.98, "nice": 0.00, "system": 20.35, "iowait": 0.18, "steal": 0.00, "idle": 21.49},
						{"cpu": "0", "user": 53.95, "nice": 0.00, "system": 24.12, "iowait": 0.25, "steal": 0.00, "idle": 21.69},
						{"cpu": "1", "user": 57.46, "nice": 0.00, "system": 22.04, "iowait": 0.77, "steal": 0.00, "idle": 19.73},
						{"cpu": "2", "user": 62.67, "nice": 0.00, "system": 13.87, "iowait": 0.14, "steal": 0.00, "idle": 23.31},
						{"cpu": "3", "user": 55.50, "nice": 0.00, "system": 22.05, "iowait": 0.00, "steal": 0.00, "idle": 22.44},
						{"cpu": "4", "user": 51.71, "nice": 0.00, "system": 26.37, "iowait": 0.00, "steal": 0.00, "idle": 21.91},
						{"cpu": "5", "user": 63.63, "nice": 0.00, "system": 12.72, "iowait": 0.00, "steal": 0.00, "idle": 23.66},
						{"cpu": "6", "user": 56.09, "nice": 0.00, "system": 21.30, "iowait": 0.00, "steal": 0.00, "idle": 22.61},
						{"cpu": "7", "user": 56.32, "nice": 0.00, "system": 23.52, "iowait": 0.00, "steal": 0.00, "idle": 20.16},
						{"cpu": "8", "user": 53.75, "nice": 0.00, "system": 24.59, "iowait": 1.63, "steal": 0.00, "idle": 20.04},
						{"cpu": "9", "user": 54.31, "nice": 0.00, "system": 26.05, "iowait": 0.14, "steal": 0.00, "idle": 19.49},
						{"cpu": "10", "user": 53.10, "nice": 0.00, "system": 26.82, "iowait": 0.04, "steal": 0.00, "idle": 20.04},
						{"cpu": "11", "user": 62.67, "nice": 0.00, "system": 15.01, "iowait": 0.00, "steal": 0.00, "idle": 22.32},
						{"cpu": "12", "user": 60.49, "nice": 0.00, "system": 14.93, "iowait": 0.92, "steal": 0.00, "idle": 23.66},
						{"cpu": "13", "user": 55.62, "nice": 0.00, "system": 22.44, "iowait": 0.04, "steal": 0.00, "idle": 21.90},
						{"cpu": "14", "user": 59.96, "nice": 0.00, "system": 16.44, "iowait": 0.07, "steal": 0.00, "idle": 23.53},
						{"cpu": "15", "user": 56.54, "nice": 0.00, "system": 21.61, "iowait": 0.18, "steal": 0.00, "idle": 21.68},
						{"cpu": "16", "user": 58.86, "nice": 0.00, "system": 18.60, "iowait": 0.00, "steal": 0.00, "idle": 22.54},
						{"cpu": "17", "user": 57.49, "nice": 0.00, "system": 21.08, "iowait": 0.67, "steal": 0.00, "idle": 20.76},
						{"cpu": "18", "user": 60.85, "nice": 0.00, "system": 15.50, "iowait": 0.00, "steal": 0.00, "idle": 23.65},
						{"cpu": "19", "user": 59.55, "nice": 0.00, "system": 18.88, "iowait": 0.67, "steal": 0.00, "idle": 20.90},
						{"cpu": "20", "user": 54.05, "nice": 0.00, "system": 26.44, "iowait": 0.00, "steal": 0.00, "idle": 19.51},
						{"cpu": "21", "user": 57.85, "nice": 0.00, "system": 19.97, "iowait": 0.00, "steal": 0.00, "idle": 22.18},
						{"cpu": "22", "user": 57.14, "nice": 0.00, "system": 22.10, "iowait": 0.64, "steal": 0.00, "idle": 20.12},
						{"cpu": "23", "user": 54.24, "nice": 0.00, "system": 25.39, "iowait": 0.00, "steal": 0.00, "idle": 20.36},
						{"cpu": "24", "user": 59.86, "nice": 0.00, "system": 20.67, "iowait": 0.00, "steal": 0.00, "idle": 19.47},
						{"cpu": "25", "user": 56.81, "nice": 0.00, "system": 21.87, "iowait": 0.49, "steal": 0.00, "idle": 20.82},
						{"cpu": "26", "user": 62.21, "nice": 0.00, "system": 12.42, "iowait": 0.18, "steal": 0.00, "idle": 25.19},
						{"cpu": "27", "user": 55.25, "nice": 0.00, "system": 23.62, "iowait": 0.00, "steal": 0.00, "idle": 21.13},
						{"cpu": "28", "user": 61.60, "nice": 0.00, "system": 13.71, "iowait": 0.00, "steal": 0.00, "idle": 24.69},
						{"cpu": "29", "user": 61.72, "nice": 0.00, "system": 14.22, "iowait": 0.00, "steal": 0.00, "idle": 24.05},
						{"cpu": "30", "user": 54.34, "nice": 0.00, "system": 25.28, "iowait": 0.00, "steal": 0.00, "idle": 20.38},
						{"cpu": "31", "user": 57.27, "nice": 0.00, "system": 19.72, "iowait": 0.14, "steal": 0.00, "idle": 22.87},
						{"cpu": "32", "user": 52.26, "nice": 0.00, "system": 33.58, "iowait": 0.00, "steal": 0.00, "idle": 14.15},
						{"cpu": "33", "user": 59.84, "nice": 0.00, "system": 17.49, "iowait": 0.25, "steal": 0.00, "idle": 22.42},
						{"cpu": "34", "user": 61.68, "nice": 0.00, "system": 16.07, "iowait": 0.04, "steal": 0.00, "idle": 22.22},
						{"cpu": "35", "user": 60.11, "nice": 0.00, "system": 18.24, "iowait": 0.00, "steal": 0.00, "idle": 21.65},
						{"cpu": "36", "user": 62.11, "nice": 0.00, "system": 17.13, "iowait": 0.25, "steal": 0.00, "idle": 20.51},
						{"cpu": "37", "user": 56.55, "nice": 0.00, "system": 23.36, "iowait": 0.00, "steal": 0.00, "idle": 20.08},
						{"cpu": "38", "user": 59.01, "nice": 0.00, "system": 20.39, "iowait": 0.18, "steal": 0.00, "idle": 20.42},
						{"cpu": "39", "user": 57.71, "nice": 0.00, "system": 22.74, "iowait": 0.46, "steal": 0.00, "idle": 19.09},
						{"cpu": "40", "user": 56.22, "nice": 0.00, "system": 23.62, "iowait": 0.00, "steal": 0.00, "idle": 20.16},
						{"cpu": "41", "user": 56.41, "nice": 0.00, "system": 22.89, "iowait": 0.04, "steal": 0.00, "idle": 20.66},
						{"cpu": "42", "user": 63.63, "nice": 0.00, "system": 14.26, "iowait": 0.18, "steal": 0.00, "idle": 21.94},
						{"cpu": "43", "user": 59.06, "nice": 0.00, "system": 18.62, "iowait": 0.00, "steal": 0.00, "idle": 22.31},
						{"cpu": "44", "user": 56.95, "nice": 0.00, "system": 25.02, "iowait": 0.60, "steal": 0.00, "idle": 17.43},
						{"cpu": "45", "user": 62.67, "nice": 0.00, "system": 13.13, "iowait": 0.18, "steal": 0.00, "idle": 24.03},
						{"cpu": "46", "user": 54.88, "nice": 0.00, "system": 24.36, "iowait": 0.00, "steal": 0.00, "idle": 20.76},
						{"cpu": "47", "user": 60.99, "nice": 0.00, "system": 15.80, "iowait": 0.00, "steal": 0.00, "idle": 23.22},
						{"cpu": "48", "user": 54.28, "nice": 0.00, "system": 24.34, "iowait": 0.00, "steal": 0.00, "idle": 21.38},
						{"cpu": "49", "user": 55.86, "nice": 0.00, "system": 21.90, "iowait": 0.00, "steal": 0.00, "idle": 22.24},
						{"cpu": "50", "user": 62.40, "nice": 0.00, "system": 13.11, "iowait": 0.00, "steal": 0.00, "idle": 24.49},
						{"cpu": "51", "user": 58.47, "nice": 0.00, "system": 19.84, "iowait": 0.50, "steal": 0.00, "idle": 21.19},
						{"cpu": "52", "user": 59.43, "nice": 0.00, "system": 20.13, "iowait": 0.25, "steal": 0.00, "idle": 20.20},
						{"cpu": "53", "user": 53.51, "nice": 0.00, "system": 25.89, "iowait": 0.00, "steal": 0.00, "idle": 20.60},
						{"cpu": "54", "user": 54.56, "nice": 0.00, "system": 24.37, "iowait": 0.00, "steal": 0.00, "idle": 21.07},
						{"cpu": "55", "user": 56.42, "nice": 0.00, "system": 22.52, "iowait": 0.80, "steal": 0.00, "idle": 20.26},
						{"cpu": "56", "user": 63.32, "nice": 0.00, "system": 12.25, "iowait": 0.00, "steal": 0.00, "idle": 24.43},
						{"cpu": "57", "user": 56.48, "nice": 0.00, "system": 22.13, "iowait": 0.00, "steal": 0.00, "idle": 21.39},
						{"cpu": "58", "user": 63.75, "nice": 0.00, "system": 11.23, "iowait": 0.00, "steal": 0.00, "idle": 25.02},
						{"cpu": "59", "user": 56.47, "nice": 0.00, "system": 22.46, "iowait": 0.00, "steal": 0.00, "idle": 21.07},
						{"cpu": "60", "user": 56.77, "nice": 0.00, "system": 22.50, "iowait": 0.00, "steal": 0.00, "idle": 20.73},
						{"cpu": "61", "user": 60.03, "nice": 0.00, "system": 18.80, "iowait": 0.00, "steal": 0.00, "idle": 21.17},
						{"cpu": "62", "user": 58.50, "nice": 0.00, "system": 18.57, "iowait": 0.66, "steal": 0.00, "idle": 22.26},
						{"cpu": "63", "user": 57.76, "nice": 0.00, "system": 21.77, "iowait": 0.00, "steal": 0.00, "idle": 20.47}
					]
				},
				{
					"timestamp": {"date": "2023-07-11", "time": "10:25:01", "utc": 1, "interval": 30},
					"cpu-load": [
						{"cpu": "all", "user": 57.86, "nice": 0.00, "system": 20.32, "iowait": 0.16, "steal": 0.00, "idle": 21.66},
						{"cpu": "0", "user": 55.96, "nice": 0.00, "system": 23.61, "iowait": 0.00, "steal": 0.00, "idle": 20.44},
						{"cpu": "1", "user": 60.08, "nice": 0.00, "system": 16.18, "iowait": 0.81, "steal": 0.00, "idle": 22.92},
						{"cpu": "2", "user": 60.82, "nice": 0.00, "system": 17.56, "iowait": 0.00, "steal": 0.00, "idle": 21.61},
						{"cpu": "3", "user": 55.74, "nice": 0.00, "system": 23.84, "iowait": 0.39, "steal": 0.00, "idle": 20.03},
						{"cpu": "4", "user": 53.57, "nice": 0.00, "system": 25.81, "iowait": 0.00, "steal": 0.00, "idle": 20.62},
						{"cpu": "5", "user": 62.15, "nice": 0.00, "system": 13.20, "iowait": 0.75, "steal": 0.00, "idle": 23.90},
						{"cpu": "6", "user": 52.95, "nice": 0.00, "system": 27.54, "iowait": 0.00, "steal": 0.00, "idle": 19.51},
						{"cpu": "7", "user": 64.94, "nice": 0.00, "system": 15.08, "iowait": 0.49, "steal": 0.00, "idle": 19.49},
						{"cpu": "8", "user": 59.58, "nice": 0.00, "system": 18.52, "iowait": 0.00, "steal": 0.00, "idle": 21.90},
						{"cpu": "9", "user": 53.85, "nice": 0.00, "system": 26.34, "iowait": 0.00, "steal": 0.00, "idle": 19.81},
						{"cpu": "10", "user": 50.64, "nice": 0.00, "system": 28.69, "iowait": 0.00, "steal": 0.00, "idle": 20.66},
						{"cpu": "11", "user": 63.39, "nice": 0.00, "system": 13.87, "iowait": 0.04, "steal": 0.00, "idle": 22.70},
						{"cpu": "12", "user": 54.63, "nice": 0.00, "system": 24.74, "iowait": 0.31, "steal": 0.00, "idle": 20.31},
						{"cpu": "13", "user": 55.99, "nice": 0.00, "system": 22.52, "iowait": 0.00, "steal": 0.00, "idle": 21.49},
						{"cpu": "14", "user": 60.43, "nice": 0.00, "system": 15.64, "iowait": 0.18, "steal": 0.00, "idle": 23.76},
						{"cpu": "15", "user": 57.45, "nice": 0.00, "system": 21.76, "iowait": 0.53, "steal": 0.00, "idle": 20.26},
						{"cpu": "16", "user": 56.21, "nice": 0.00, "system": 19.96, "iowait": 0.00, "steal": 0.00, "idle": 23.83},
						{"cpu": "17", "user": 58.05, "nice": 0.00, "system": 17.84, "iowait": 0.00, "steal": 0.00, "idle": 24.11},
						{"cpu": "18", "user": 50.40, "nice": 0.00, "system": 33.40, "iowait": 1.00, "steal": 0.00, "idle": 15.20},
						{"cpu": "19", "user": 62.07, "nice": 0.00, "system": 12.86, "iowait": 0.00, "steal": 0.00, "idle": 25.06},
						{"cpu": "20", "user": 50.95, "nice": 0.00, "system": 27.88, "iowait": 0.00, "steal": 0.00, "idle": 21.17},
						{"cpu": "21", "user": 58.22, "nice": 0.00, "system": 19.17, "iowait": 0.00, "steal": 0.00, "idle": 22.60},
						{"cpu": "22", "user": 63.07, "nice": 0.00, "system": 11.14, "iowait": 0.00, "steal": 0.00, "idle": 25.79},
						{"cpu": "23", "user": 54.69, "nice": 0.00, "system": 23.92, "iowait": 0.00, "steal": 0.00, "idle": 21.38},
						{"cpu": "24", "user": 61.70, "nice": 0.00, "system": 13.51, "iowait": 0.00, "steal": 0.00, "idle": 24.79},
						{"cpu": "25", "user": 57.74, "nice": 0.00, "system": 18.62, "iowait": 0.00, "steal": 0.00, "idle": 23.64},
						{"cpu": "26", "user": 60.75, "nice": 0.00, "system": 17.04, "iowait": 0.99, "steal": 0.00, "idle": 21.22},
						{"cpu": "27", "user": 55.24, "nice": 0.00, "system": 23.93, "iowait": 0.00, "steal": 0.00, "idle": 20.83},
						{"cpu": "28", "user": 61.81, "nice": 0.00, "system": 13.91, "iowait": 0.00, "steal": 0.00, "idle": 24.28},
						{"cpu": "29", "user": 58.22, "nice": 0.00, "system": 19.52, "iowait": 0.84, "steal": 0.00, "idle": 21.41},
						{"cpu": "30", "user": 49.86, "nice": 0.00, "system": 29.60, "iowait": 0.00, "steal": 0.00, "idle": 20.55},
						{"cpu": "31", "user": 59.29, "nice": 0.00, "system": 17.29, "iowait": 0.00, "steal": 0.00, "idle": 23.42},
						{"cpu": "32", "user": 60.47, "nice": 0.00, "system": 15.68, "iowait": 0.85, "steal": 0.00, "idle": 23.00},
						{"cpu": "33", "user": 58.91, "nice": 0.00, "system": 17.82, "iowait": 0.00, "steal": 0.00, "idle": 23.27},
						{"cpu": "34", "user": 59.67, "nice": 0.00, "system": 15.81, "iowait": 0.11, "steal": 0.00, "idle": 24.42},
						{"cpu": "35", "user": 58.62, "nice": 0.00, "system": 18.11, "iowait": 0.18, "steal": 0.00, "idle": 23.08},
						{"cpu": "36", "user": 56.84, "nice": 0.00, "system": 22.02, "iowait": 0.00, "steal": 0.00, "idle": 21.14},
						{"cpu": "37", "user": 54.73, "nice": 0.00, "system": 23.99, "iowait": 0.00, "steal": 0.00, "idle": 21.28},
						{"cpu": "38", "user": 57.53, "nice": 0.00, "system": 21.06, "iowait": 0.04, "steal": 0.00, "idle": 21.38},
						{"cpu": "39", "user": 57.43, "nice": 0.00, "system": 20.65, "iowait": 0.00, "steal": 0.00, "idle": 21.93},
						{"cpu": "40", "user": 54.65, "nice": 0.00, "system": 22.62, "iowait": 0.18, "steal": 0.00, "idle": 22.55},
						{"cpu": "41", "user": 54.71, "nice": 0.00, "system": 24.16, "iowait": 0.00, "steal": 0.00, "idle": 21.13},
						{"cpu": "42", "user": 58.29, "nice": 0.00, "system": 19.71, "iowait": 0.91, "steal": 0.00, "idle": 21.08},
						{"cpu": "43", "user": 56.33, "nice": 0.00, "system": 19.67, "iowait": 0.00, "steal": 0.00, "idle": 23.99},
						{"cpu": "44", "user": 54.78, "nice": 0.00, "system": 23.26, "iowait": 0.00, "steal": 0.00, "idle": 21.96},
						{"cpu": "45", "user": 61.64, "nice": 0.00, "system": 13.33, "iowait": 0.00, "steal": 0.00, "idle": 25.04},
						{"cpu": "46", "user": 55.12, "nice": 0.00, "system": 22.90, "iowait": 0.00, "steal": 0.00, "idle": 21.98},
						{"cpu": "47", "user": 58.52, "nice": 0.00, "system": 20.35, "iowait": 0.00, "steal": 0.00, "idle": 21.13},
						{"cpu": "48", "user": 55.96, "nice": 0.00, "system": 23.69, "iowait": 0.00, "steal": 0.00, "idle": 20.35},
						{"cpu": "49", "user": 58.61, "nice": 0.00, "system": 20.89, "iowait": 0.18, "steal": 0.00, "idle": 20.32},
						{"cpu": "50", "user": 63.12, "nice": 0.00, "system": 13.06, "iowait": 0.00, "steal": 0.00, "idle": 23.82},
						{"cpu": "51", "user": 60.17, "nice": 0.00, "system": 18.07, "iowait": 0.03, "steal": 0.00, "idle": 21.73},
						{"cpu": "52", "user": 57.72, "nice": 0.00, "system": 23.20, "iowait": 0.49, "steal": 0.00, "idle": 18.59},
						{"cpu": "53", "user": 55.61, "nice": 0.00, "system": 23.48, "iowait": 0.00, "steal": 0.00, "idle": 20.91},
						{"cpu": "54", "user": 54.34, "nice": 0.00, "system": 26.32, "iowait": 0.00, "steal": 0.00, "idle": 19.34},
						{"cpu": "55", "user": 63.24, "nice": 0.00, "system": 14.58, "iowait": 0.00, "steal": 0.00, "idle": 22.18},
						{"cpu": "56", "user": 65.46, "nice": 0.00, "system": 10.93, "iowait": 0.00, "steal": 0.00, "idle": 23.61},
						{"cpu": "57", "user": 54.16, "nice": 0.00, "system": 26.75, "iowait": 0.00, "steal": 0.00, "idle": 19.09},
						{"cpu": "58", "user": 57.20, "nice": 0.00, "system": 24.72, "iowait": 0.00, "steal": 0.00, "idle": 18.09},
						{"cpu": "59", "user": 60.04, "nice": 0.00, "system": 18.84, "iowait": 0.00, "steal": 0.00, "idle": 21.12},
						{"cpu": "60", "user": 57.66, "nice": 0.00, "system": 23.19, "iowait": 0.00, "steal": 0.00, "idle": 19.15},
						{"cpu": "61", "user": 62.19, "nice": 0.00, "system": 19.32, "iowait": 1.04, "steal": 0.00, "idle": 17.45},
						{"cpu": "62", "user": 62.52, "nice": 0.00, "system": 13.01, "iowait": 0.00, "steal": 0.00, "idle": 24.47},
						{"cpu": "63", "user": 55.78, "nice": 0.00, "system": 24.67, "iowait": 0.00, "steal": 0.00, "idle": 19.55}
					]
				},
				{
					"timestamp": {"date": "2023-07-11", "time": "10:25:31", "utc": 1, "interval": 30},
					"cpu-load": [
						{"cpu": "all", "user": 58.88, "nice": 0.00, "system": 20.24, "iowait": 0.13, "steal": 0.00, "idle": 20.75},
						{"cpu": "0", "user": 56.18, "nice": 0.00, "system": 22.31, "iowait": 0.00, "steal": 0.00, "idle": 21.51},
						{"cpu": "1", "user": 59.29, "nice": 0.00, "system": 18.76, "iowait": 0.04, "steal": 0.00, "idle": 21.91},
						{"cpu": "2", "user": 67.78, "nice": 0.00, "system": 12.93, "iowait": 0.00, "steal": 0.00, "idle": 19.29},
						{"cpu": "3", "user": 59.19, "nice": 0.00, "system": 20.33, "iowait": 0.00, "steal": 0.00, "idle": 20.48},
						{"cpu": "4", "user": 53.30, "nice": 0.00, "system": 26.69, "iowait": 0.00, "steal": 0.00, "idle": 20.01},
						{"cpu": "5", "user": 56.72, "nice": 0.00, "system": 22.01, "iowait": 0.00, "steal": 0.00, "idle": 21.27},
						{"cpu": "6", "user": 55.41, "nice": 0.00, "system": 21.92, "iowait": 0.00, "steal": 0.00, "idle": 22.67},
						{"cpu": "7", "user": 57.13, "nice": 0.00, "system": 20.98, "iowait": 0.84, "steal": 0.00, "idle": 21.05},
						{"cpu": "8", "user": 56.88, "nice": 0.00, "system": 20.29, "iowait": 0.43, "steal": 0.00, "idle": 22.40},
						{"cpu": "9", "user": 52.97, "nice": 0.00, "system": 26.77, "iowait": 0.18, "steal": 0.00, "idle": 20.08},
						{"cpu": "10", "user": 49.98, "nice": 0.00, "system": 28.43, "iowait": 0.00, "steal": 0.00, "idle": 21.59},
						{"cpu": "11", "user": 64.14, "nice": 0.00, "system": 12.83, "iowait": 0.00, "steal": 0.00, "idle": 23.03},
						{"cpu": "12", "user": 62.38, "nice": 0.00, "system": 12.91, "iowait": 0.00, "steal": 0.00, "idle": 24.72},
						{"cpu": "13", "user": 54.24, "nice": 0.00, "system": 24.34, "iowait": 0.36, "steal": 0.00, "idle": 21.05},
						{"cpu": "14", "user": 59.07, "nice": 0.00, "system": 20.06, "iowait": 0.84, "steal": 0.00, "idle": 20.03},
						{"cpu": "15", "user": 55.53, "nice": 0.00, "system": 22.29, "iowait": 0.11, "steal": 0.00, "idle": 22.08},
						{"cpu": "16", "user": 57.83, "nice": 0.00, "system": 20.99, "iowait": 0.14, "steal": 0.00, "idle": 21.03},
						{"cpu": "17", "user": 52.57, "nice": 0.00, "system": 29.63, "iowait": 0.56, "steal": 0.00, "idle": 17.24},
						{"cpu": "18", "user": 62.66, "nice": 0.00, "system": 17.32, "iowait": 0.00, "steal": 0.00, "idle": 20.02},
						{"cpu": "19", "user": 58.78, "nice": 0.00, "system": 19.98, "iowait": 0.28, "steal": 0.00, "idle": 20.96},
						{"cpu": "20", "user": 54.07, "nice": 0.00, "system": 26.18, "iowait": 0.14, "steal": 0.00, "idle": 19.61},
						{"cpu": "21", "user": 58.80, "nice": 0.00, "system": 20.21, "iowait": 0.04, "steal": 0.00, "idle": 20.96},
						{"cpu": "22", "user": 63.69, "nice": 0.00, "system": 12.18, "iowait": 0.00, "steal": 0.00, "idle": 24.12},
						{"cpu": "23", "user": 53.48, "nice": 0.00, "system": 26.84, "iowait": 0.00, "steal": 0.00, "idle": 19.68},
						{"cpu": "24", "user": 61.78, "nice": 0.00, "system": 14.56, "iowait": 0.28, "steal": 0.00, "idle": 23.38},
						{"cpu": "25", "user": 59.50, "nice": 0.00, "system": 18.34, "iowait": 0.00, "steal": 0.00, "idle": 22.16},
						{"cpu": "26", "user": 61.82, "nice": 0.00, "system": 15.41, "iowait": 0.67, "steal": 0.00, "idle": 22.10},
						{"cpu": "27", "user": 56.53, "nice": 0.00, "system": 23.19, "iowait": 0.00, "steal": 0.00, "idle": 20.28},
						{"cpu": "28", "user": 61.67, "nice": 0.00, "system": 14.74, "iowait": 0.00, "steal": 0.00, "idle": 23.59},
						{"cpu": "29", "user": 63.56, "nice": 0.00, "system": 16.06, "iowait": 0.00, "steal": 0.00, "idle": 20.38},
						{"cpu": "30", "user": 54.17, "nice": 0.00, "system": 28.44, "iowait": 0.00, "steal": 0.00, "idle": 17.39},
						{"cpu": "31", "user": 60.17, "nice": 0.00, "system": 19.09, "iowait": 0.00, "steal": 0.00, "idle": 20.74},
						{"cpu": "32", "user": 57.40, "nice": 0.00, "system": 21.67, "iowait": 0.78, "steal": 0.00, "idle": 20.15},
						{"cpu": "33", "user": 60.47, "nice": 0.00, "system": 17.20, "iowait": 0.00, "steal": 0.00, "idle": 22.32},
						{"cpu": "34", "user": 64.66, "nice": 0.00, "system": 12.71, "iowait": 0.00, "steal": 0.00, "idle": 22.63},
						{"cpu": "35", "user": 58.17, "nice": 0.00, "system": 19.89, "iowait": 0.00, "steal": 0.00, "idle": 21.94},
						{"cpu": "36", "user": 60.67, "nice": 0.00, "system": 18.35, "iowait": 0.00, "steal": 0.00, "idle": 20.98},
						{"cpu": "37", "user": 55.09, "nice": 0.00, "system": 24.28, "iowait": 0.00, "steal": 0.00, "idle": 20.63},
						{"cpu": "38", "user": 58.90, "nice": 0.00, "system": 20.08, "iowait": 0.00, "steal": 0.00, "idle": 21.02},
						{"cpu": "39", "user": 58.39, "nice": 0.00, "system": 20.16, "iowait": 0.00, "steal": 0.00, "idle": 21.45},
						{"cpu": "40", "user": 56.31, "nice": 0.00, "system": 21.47, "iowait": 0.00, "steal": 0.00, "idle": 22.22},
						{"cpu": "41", "user": 51.32, "nice": 0.00, "system": 29.91, "iowait": 0.00, "steal": 0.00, "idle": 18.78},
						{"cpu": "42", "user": 60.61, "nice": 0.00, "system": 14.45, "iowait": 0.04, "steal": 0.00, "idle": 24.90},
						{"cpu": "43", "user": 58.39, "nice": 0.00, "system": 21.61, "iowait": 0.11, "steal": 0.00, "idle": 19.89},
						{"cpu": "44", "user": 55.73, "nice": 0.00, "system": 21.80, "iowait": 0.00, "steal": 0.00, "idle": 22.48},
						{"cpu": "45", "user": 60.66, "nice": 0.00, "system": 17.80, "iowait": 0.00, "steal": 0.00, "idle": 21.54},
						{"cpu": "46", "user": 53.97, "nice": 0.00, "system": 25.42, "iowait": 0.00, "steal": 0.00, "idle": 20.60},
						{"cpu": "47", "user": 59.99, "nice": 0.00, "system": 18.04, "iowait": 0.04, "steal": 0.00, "idle": 21.94},
						{"cpu": "48", "user": 56.87, "nice": 0.00, "system": 24.43, "iowait": 0.39, "steal": 0.00, "idle": 18.32},
						{"cpu": "49", "user": 58.85, "nice": 0.00, "system": 23.48, "iowait": 0.18, "steal": 0.00, "idle": 17.49},
						{"cpu": "50", "user": 64.10, "nice": 0.00, "system": 14.30, "iowait": 0.00, "steal": 0.00, "idle": 21.60},
						{"cpu": "51", "user": 59.16, "nice": 0.00, "system": 18.11, "iowait": 0.00, "steal": 0.00, "idle": 22.73},
						{"cpu": "52", "user": 65.90, "nice": 0.00, "system": 13.54, "iowait": 0.31, "steal": 0.00, "idle": 20.25},
						{"cpu": "53", "user": 60.00, "nice": 0.00, "system": 21.70, "iowait": 0.00, "steal": 0.00, "idle": 18.30},
						{"cpu": "54", "user": 54.93, "nice": 0.00, "system": 27.77, "iowait": 0.14, "steal": 0.00, "idle": 17.16},
						{"cpu": "55", "user": 66.75, "nice": 0.00, "system": 13.12, "iowait": 0.11, "steal": 0.00, "idle": 20.02},
						{"cpu": "56", "user": 59.05, "nice": 0.00, "system": 25.08, "iowait": 0.44, "steal": 0.00, "idle": 15.43},
						{"cpu": "57", "user": 60.79, "nice": 0.00, "system": 20.09, "iowait": 0.22, "steal": 0.00, "idle": 18.90},
						{"cpu": "58", "user": 65.29, "nice": 0.00, "system": 13.32, "iowait": 0.17, "steal": 0.00, "idle": 21.22},
						{"cpu": "59", "user": 60.99, "nice": 0.00, "system": 19.06, "iowait": 0.14, "steal": 0.00, "idle": 19.81},
						{"cpu": "60", "user": 59.24, "nice": 0.00, "system": 21.95, "iowait": 0.00, "steal": 0.00, "idle": 18.81},
						{"cpu": "61", "user": 62.70, "nice": 0.00, "system": 17.52, "iowait": 0.00, "steal": 0.00, "idle": 19.78},
						{"cpu": "62", "user": 62.87, "nice": 0.00, "system": 17.25, "iowait": 0.28, "steal": 0.00, "idle": 19.61},
						{"cpu": "63", "user": 57.81, "nice": 0.00, "system": 23.34, "iowait": 0.00, "steal": 0.00, "idle": 18.85}
					]
				},
				{
					"timestamp": {"date": "2023-07-11", "time": "10:26:01", "utc": 1, "interval": 30},
					"cpu-load": [
						{"cpu": "all", "user": 60.05, "nice": 0.00, "system": 19.52, "iowait": 0.31, "steal": 0.00, "idle": 20.12},
						{"cpu": "0", "user": 58.85, "nice": 0.00, "system": 24.16, "iowait": 0.00, "steal": 0.00, "idle": 16.99},
						{"cpu": "1", "user": 61.65, "nice": 0.00, "system": 23.29, "iowait": 0.14, "steal": 0.00, "idle": 14.93},
						{"cpu": "2", "user": 68.37, "nice": 0.00, "system": 12.80, "iowait": 0.00, "steal": 0.00, "idle": 18.83},
						{"cpu": "3", "user": 56.77, "nice": 0.00, "system": 24.55, "iowait": 0.03, "steal": 0.00, "idle": 18.64},
						{"cpu": "4", "user": 58.92, "nice": 0.00, "system": 24.85, "iowait": 0.07, "steal": 0.00, "idle": 16.16},
						{"cpu": "5", "user": 64.64, "nice": 0.00, "system": 14.55, "iowait": 0.24, "steal": 0.00, "idle": 20.57},
						{"cpu": "6", "user": 60.64, "nice": 0.00, "system": 20.96, "iowait": 0.00, "steal": 0.00, "idle": 18.40},
						{"cpu": "7", "user": 62.45, "nice": 0.00, "system": 19.98, "iowait": 0.03, "steal": 0.00, "idle": 17.53},
						{"cpu": "8", "user": 65.36, "nice": 0.00, "system": 17.04, "iowait": 0.00, "steal": 0.00, "idle": 17.60},
						{"cpu": "9", "user": 57.20, "nice": 0.00, "system": 26.63, "iowait": 0.00, "steal": 0.00, "idle": 16.17},
						{"cpu": "10", "user": 55.94, "nice": 0.00, "system": 26.75, "iowait": 0.03, "steal": 0.00, "idle": 17.28},
						{"cpu": "11", "user": 67.08, "nice": 0.00, "system": 13.47, "iowait": 0.00, "steal": 0.00, "idle": 19.45},
						{"cpu": "12", "user": 63.18, "nice": 0.00, "system": 16.40, "iowait": 0.48, "steal": 0.00, "idle": 19.94},
						{"cpu": "13", "user": 61.33, "nice": 0.00, "system": 21.02, "iowait": 0.00, "steal": 0.00, "idle": 17.65},
						{"cpu": "14", "user": 65.77, "nice": 0.00, "system": 18.07, "iowait": 0.17, "steal": 0.00, "idle": 15.98},
						{"cpu": "15", "user": 61.50, "nice": 0.00, "system": 21.24, "iowait": 0.00, "steal": 0.00, "idle": 17.25},
						{"cpu": "16", "user": 59.66, "nice": 0.00, "system": 18.64, "iowait": 0.00, "steal": 0.00, "idle": 21.70},
						{"cpu": "17", "user": 58.79, "nice": 0.00, "system": 18.55, "iowait": 0.11, "steal": 0.00, "idle": 22.56},
						{"cpu": "18", "user": 63.54, "nice": 0.00, "system": 16.22, "iowait": 0.00, "steal": 0.00, "idle": 20.25},
						{"cpu": "19", "user": 72.51, "nice": 0.00, "system": 15.64, "iowait": 0.78, "steal": 0.00, "idle": 11.07},
						{"cpu": "20", "user": 57.09, "nice": 0.00, "system": 23.15, "iowait": 0.00, "steal": 0.00, "idle": 19.76},
						{"cpu": "21", "user": 57.53, "nice": 0.00, "system": 22.37, "iowait": 0.00, "steal": 0.00, "idle": 20.10},
						{"cpu": "22", "user": 66.14, "nice": 0.00, "system": 15.85, "iowait": 1.50, "steal": 0.00, "idle": 16.51},
						{"cpu": "23", "user": 55.82, "nice": 0.00, "system": 24.28, "iowait": 0.98, "steal": 0.00, "idle": 18.91},
						{"cpu": "24", "user": 63.81, "nice": 0.00, "system": 13.98, "iowait": 0.14, "steal": 0.00, "idle": 22.07},
						{"cpu": "25", "user": 58.40, "nice": 0.00, "system": 19.59, "iowait": 0.07, "steal": 0.00, "idle": 21.94},
						{"cpu": "26", "user": 66.52, "nice": 0.00, "system": 10.79, "iowait": 0.03, "steal": 0.00, "idle": 22.66},
						{"cpu": "27", "user": 54.44, "nice": 0.00, "system": 24.46, "iowait": 0.00, "steal": 0.00, "idle": 21.10},
						{"cpu": "28", "user": 56.44, "nice": 0.00, "system": 23.63, "iowait": 1.79, "steal": 0.00, "idle": 18.14},
						{"cpu": "29", "user": 62.66, "nice": 0.00, "system": 16.31, "iowait": 0.00, "steal": 0.00, "idle": 21.03},
						{"cpu": "30", "user": 54.76, "nice": 0.00, "system": 25.84, "iowait": 0.00, "steal": 0.00, "idle": 19.40},
						{"cpu": "31", "user": 60.05, "nice": 0.00, "system": 18.92, "iowait": 0.00, "steal": 0.00, "idle": 21.03},
						{"cpu": "32", "user": 65.99, "nice": 0.00, "system": 11.92, "iowait": 0.04, "steal": 0.00, "idle": 22.05},
						{"cpu": "33", "user": 60.03, "nice": 0.00, "system": 24.34, "iowait": 0.59, "steal": 0.00, "idle": 15.04},
						{"cpu": "34", "user": 61.80, "nice": 0.00, "system": 18.98, "iowait": 0.96, "steal": 0.00, "idle": 18.26},
						{"cpu": "35", "user": 59.09, "nice": 0.00, "system": 19.08, "iowait": 0.00, "steal": 0.00, "idle": 21.83},
						{"cpu": "36", "user": 58.95, "nice": 0.00, "system": 21.40, "iowait": 1.43, "steal": 0.00, "idle": 18.22},
						{"cpu": "37", "user": 56.25, "nice": 0.00, "system": 24.19, "iowait": 0.00, "steal": 0.00, "idle": 19.55},
						{"cpu": "38", "user": 58.37, "nice": 0.00, "system": 21.39, "iowait": 0.00, "steal": 0.00, "idle": 20.24},
						{"cpu": "39", "user": 58.96, "nice": 0.00, "system": 20.41, "iowait": 0.00, "steal": 0.00, "idle": 20.63},
						{"cpu": "40", "user": 59.59, "nice": 0.00, "system": 19.15, "iowait": 0.00, "steal": 0.00, "idle": 21.26},
						{"cpu": "41", "user": 55.75, "nice": 0.00, "system": 24.98, "iowait": 0.00, "steal": 0.00, "idle": 19.26},
						{"cpu": "42", "user": 63.50, "nice": 0.00, "system": 13.59, "iowait": 0.18, "steal": 0.00, "idle": 22.73},
						{"cpu": "43", "user": 56.40, "nice": 0.00, "system": 21.44, "iowait": 0.00, "steal": 0.00, "idle": 22.16},
						{"cpu": "44", "user": 55.29, "nice": 0.00, "system": 23.28, "iowait": 0.04, "steal": 0.00, "idle": 21.40},
						{"cpu": "45", "user": 66.10, "nice": 0.00, "system": 12.29, "iowait": 0.78, "steal": 0.00, "idle": 20.83},
						{"cpu": "46", "user": 66.62, "nice": 0.00, "system": 16.74, "iowait": 0.00, "steal": 0.00, "idle": 16.64},
						{"cpu": "47", "user": 66.12, "nice": 0.00, "system": 12.53, "iowait": 1.09, "steal": 0.00, "idle": 20.27},
						{"cpu": "48", "user": 55.75, "nice": 0.00, "system": 21.34, "iowait": 0.00, "steal": 0.00, "idle": 22.91},
						{"cpu": "49", "user": 56.07, "nice": 0.00, "system": 20.89, "iowait": 0.74, "steal": 0.00, "idle": 22.30},
						{"cpu": "50", "user": 57.68, "nice": 0.00, "system": 18.72, "iowait": 0.62, "steal": 0.00, "idle": 22.98},
						{"cpu": "51", "user": 60.10, "nice": 0.00, "system": 16.87, "iowait": 0.00, "steal": 0.00, "idle": 23.03},
						{"cpu": "52", "user": 59.88, "nice": 0.00, "system": 17.26, "iowait": 1.25, "steal": 0.00, "idle": 21.60},
						{"cpu": "53", "user": 56.73, "nice": 0.00, "system": 21.71, "iowait": 0.00, "steal": 0.00, "idle": 21.57},
						{"cpu": "54", "user": 52.79, "nice": 0.00, "system": 24.55, "iowait": 1.82, "steal": 0.00, "idle": 20.83},
						{"cpu": "55", "user": 54.51, "nice": 0.00, "system": 23.24, "iowait": 0.93, "steal": 0.00, "idle": 21.31},
						{"cpu": "56", "user": 61.94, "nice": 0.00, "system": 14.83, "iowait": 0.91, "steal": 0.00, "idle": 22.32},
						{"cpu": "57", "user": 56.03, "nice": 0.00, "system": 20.20, "iowait": 0.49, "steal": 0.00, "idle": 23.27},
						{"cpu": "58", "user": 55.13, "nice": 0.00, "system": 22.07, "iowait": 0.56, "steal": 0.00, "idle": 22.24},
						{"cpu": "59", "user": 56.97, "nice": 0.00, "system": 20.32, "iowait": 0.14, "steal": 0.00, "idle": 22.56},
						{"cpu": "60", "user": 54.31, "nice": 0.00, "system": 22.41, "iowait": 0.07, "steal": 0.00, "idle": 23.21},
						{"cpu": "61", "user": 62.09, "nice": 0.00, "system": 11.00, "iowait": 0.00, "steal": 0.00, "idle": 26.91},
						{"cpu": "62", "user": 61.54, "nice": 0.00, "system": 11.47, "iowait": 0.11, "steal": 0.00, "idle": 26.88},
						{"cpu": "63", "user": 54.38, "nice": 0.00, "system": 23.26, "iowait": 0.39, "steal": 0.00, "idle": 21.97}
					]
				},
				{
					"timestamp": {"date": "2023-07-11", "time": "10:26:31", "utc": 1, "interval": 30},
					"cpu-load": [
						{"cpu": "all", "user": 58.89, "nice": 0.00, "system": 19.54, "iowait": 0.36, "steal": 0.00, "idle": 21.21},
						{"cpu": "0", "user": 54.43, "nice": 0.00, "system": 23.23, "iowait": 0.18, "steal": 0.00, "idle": 22.16},
						{"cpu": "1", "user": 62.10, "nice": 0.00, "system": 14.54, "iowait": 0.00, "steal": 0.00, "idle": 23.36},
						{"cpu": "2", "user": 59.68, "nice": 0.00, "system": 20.59, "iowait": 1.86, "steal": 0.00, "idle": 17.87},
						{"cpu": "3", "user": 55.24, "nice": 0.00, "system": 20.55, "iowait": 0.14, "steal": 0.00, "idle": 24.07},
						{"cpu": "4", "user": 67.10, "nice": 0.00, "system": 14.26, "iowait": 0.10, "steal": 0.00, "idle": 18.54},
						{"cpu": "5", "user": 59.68, "nice": 0.00, "system": 17.41, "iowait": 0.10, "steal": 0.00, "idle": 22.81},
						{"cpu": "6", "user": 53.91, "nice": 0.00, "system": 22.19, "iowait": 1.30, "steal": 0.00, "idle": 22.61},
						{"cpu": "7", "user": 59.02, "nice": 0.00, "system": 13.68, "iowait": 0.00, "steal": 0.00, "idle": 27.30},
						{"cpu": "8", "user": 54.51, "nice": 0.00, "system": 22.74, "iowait": 0.88, "steal": 0.00, "idle": 21.86},
						{"cpu": "9", "user": 49.71, "nice": 0.00, "system": 28.17, "iowait": 0.00, "steal": 0.00, "idle": 22.12},
						{"cpu": "10", "user": 50.79, "nice": 0.00, "system": 26.63, "iowait": 0.07, "steal": 0.00, "idle": 22.51},
						{"cpu": "11", "user": 59.94, "nice": 0.00, "system": 12.94, "iowait": 0.00, "steal": 0.00, "idle": 27.12},
						{"cpu": "12", "user": 62.47, "nice": 0.00, "system": 13.26, "iowait": 0.29, "steal": 0.00, "idle": 23.98},
						{"cpu": "13", "user": 52.66, "nice": 0.00, "system": 23.21, "iowait": 0.46, "steal": 0.00, "idle": 23.67},
						{"cpu": "14", "user": 58.68, "nice": 0.00, "system": 22.49, "iowait": 1.64, "steal": 0.00, "idle": 17.19},
						{"cpu": "15", "user": 52.16, "nice": 0.00, "system": 24.90, "iowait": 0.00, "steal": 0.00, "idle": 22.94},
						{"cpu": "16", "user": 67.68, "nice": 0.00, "system": 15.14, "iowait": 0.00, "steal": 0.00, "idle": 17.19},
						{"cpu": "17", "user": 63.57, "nice": 0.00, "system": 16.01, "iowait": 0.00, "steal": 0.00, "idle": 20.42},
						{"cpu": "18", "user": 58.57, "nice": 0.00, "system": 24.05, "iowait": 0.86, "steal": 0.00, "idle": 16.52},
						{"cpu": "19", "user": 68.59, "nice": 0.00, "system": 12.20, "iowait": 0.03, "steal": 0.00, "idle": 19.18},
						{"cpu": "20", "user": 55.47, "nice": 0.00, "system": 26.20, "iowait": 0.56, "steal": 0.00, "idle": 17.77},
						{"cpu": "21", "user": 61.49, "nice": 0.00, "system": 18.85, "iowait": 0.00, "steal": 0.00, "idle": 19.66},
						{"cpu": "22", "user": 67.68, "nice": 0.00, "system": 12.21, "iowait": 0.28, "steal": 0.00, "idle": 19.83},
						{"cpu": "23", "user": 58.36, "nice": 0.00, "system": 23.84, "iowait": 0.07, "steal": 0.00, "idle": 17.73},
						{"cpu": "24", "user": 64.59, "nice": 0.00, "system": 14.07, "iowait": 0.18, "steal": 0.00, "idle": 21.16},
						{"cpu": "25", "user": 63.67, "nice": 0.00, "system": 16.10, "iowait": 0.00, "steal": 0.00, "idle": 20.23},
						{"cpu": "26", "user": 56.88, "nice": 0.00, "system": 25.06, "iowait": 0.20, "steal": 0.00, "idle": 17.86},
						{"cpu": "27", "user": 57.52, "nice": 0.00, "system": 22.35, "iowait": 0.00, "steal": 0.00, "idle": 20.13},
						{"cpu": "28", "user": 60.87, "nice": 0.00, "system": 18.30, "iowait": 1.05, "steal": 0.00, "idle": 19.78},
						{"cpu": "29", "user": 64.71, "nice": 0.00, "system": 13.61, "iowait": 0.07, "steal": 0.00, "idle": 21.62},
						{"cpu": "30", "user": 56.60, "nice": 0.00, "system": 25.10, "iowait": 0.41, "steal": 0.00, "idle": 17.88},
						{"cpu": "31", "user": 60.55, "nice": 0.00, "system": 19.18, "iowait": 0.95, "steal": 0.00, "idle": 19.32},
						{"cpu": "32", "user": 71.29, "nice": 0.00, "system": 8.36, "iowait": 0.00, "steal": 0.00, "idle": 20.36},
						{"cpu": "33", "user": 59.44, "nice": 0.00, "system": 19.70, "iowait": 0.89, "steal": 0.00, "idle": 19.97},
						{"cpu": "34", "user": 60.25, "nice": 0.00, "system": 20.81, "iowait": 0.34, "steal": 0.00, "idle": 18.59},
						{"cpu": "35", "user": 59.09, "nice": 0.00, "system": 20.62, "iowait": 0.99, "steal": 0.00, "idle": 19.31},
						{"cpu": "36", "user": 63.10, "nice": 0.00, "system": 16.95, "iowait": 0.11, "steal": 0.00, "idle": 19.85},
						{"cpu": "37", "user": 56.39, "nice": 0.00, "system": 24.79, "iowait": 0.00, "steal": 0.00, "idle": 18.82},
						{"cpu": "38", "user": 53.79, "nice": 0.00, "system": 28.01, "iowait": 0.00, "steal": 0.00, "idle": 18.20},
						{"cpu": "39", "user": 59.41, "nice": 0.00, "system": 19.99, "iowait": 0.11, "steal": 0.00, "idle": 20.49},
						{"cpu": "40", "user": 59.41, "nice": 0.00, "system": 20.24, "iowait": 0.44, "steal": 0.00, "idle": 19.91},
						{"cpu": "41", "user": 58.29, "nice": 0.00, "system": 22.77, "iowait": 0.04, "steal": 0.00, "idle": 18.91},
						{"cpu": "42", "user": 61.63, "nice": 0.00, "system": 15.08, "iowait": 0.39, "steal": 0.00, "idle": 22.90},
						{"cpu": "43", "user": 58.32, "nice": 0.00, "system": 22.43, "iowait": 0.83, "steal": 0.00, "idle": 18.41},
						{"cpu": "44", "user": 54.89, "nice": 0.00, "system": 26.30, "iowait": 0.00, "steal": 0.00, "idle": 18.81},
						{"cpu": "45", "user": 64.27, "nice": 0.00, "system": 13.10, "iowait": 0.21, "steal": 0.00, "idle": 22.43},
						{"cpu": "46", "user": 59.91, "nice": 0.00, "system": 24.02, "iowait": 0.34, "steal": 0.00, "idle": 15.73},
						{"cpu": "47", "user": 64.04, "nice": 0.00, "system": 15.09, "iowait": 0.89, "steal": 0.00, "idle": 19.99},
						{"cpu": "48", "user": 55.70, "nice": 0.00, "system": 20.46, "iowait": 0.07, "steal": 0.00, "idle": 23.77},
						{"cpu": "49", "user": 54.44, "nice": 0.00, "system": 24.11, "iowait": 0.35, "steal": 0.00, "idle": 21.10},
						{"cpu": "50", "user": 61.72, "nice": 0.00, "system": 11.73, "iowait": 0.00, "steal": 0.00, "idle": 26.55},
						{"cpu": "51", "user": 58.35, "nice": 0.00, "system": 16.22, "iowait": 0.07, "steal": 0.00, "idle": 25.36},
						{"cpu": "52", "user": 59.47, "nice": 0.00, "system": 15.77, "iowait": 0.07, "steal": 0.00, "idle": 24.69},
						{"cpu": "53", "user": 53.54, "nice": 0.00, "system": 23.35, "iowait": 0.00, "steal": 0.00, "idle": 23.11},
						{"cpu": "54", "user": 53.61, "nice": 0.00, "system": 24.38, "iowait": 0.00, "steal": 0.00, "idle": 22.01},
						{"cpu": "55", "user": 59.93, "nice": 0.00, "system": 15.30, "iowait": 0.91, "steal": 0.00, "idle": 23.86},
						{"cpu": "56", "user": 55.06, "nice": 0.00, "system": 22.26, "iowait": 1.01, "steal": 0.00, "idle": 21.67},
						{"cpu": "57", "user": 55.16, "nice": 0.00, "system": 21.49, "iowait": 0.14, "steal": 0.00, "idle": 23.21},
						{"cpu": "58", "user": 57.45, "nice": 0.00, "system": 18.66, "iowait": 1.28, "steal": 0.00, "idle": 22.62},
						{"cpu": "59", "user": 50.11, "nice": 0.00, "system": 27.51, "iowait": 0.63, "steal": 0.00, "idle": 21.75},
						{"cpu": "60", "user": 54.96, "nice": 0.00, "system": 21.34, "iowait": 0.49, "steal": 0.00, "idle": 23.21},
						{"cpu": "61", "user": 62.47, "nice": 0.00, "system": 11.56, "iowait": 0.11, "steal": 0.00, "idle": 25.86},
						{"cpu": "62", "user": 59.10, "nice": 0.00, "system": 13.89, "iowait": 0.18, "steal": 0.00, "idle": 26.83},
						{"cpu": "63", "user": 54.17, "nice": 0.00, "system": 21.53, "iowait": 0.54, "steal": 0.00, "idle": 23.75}
					]
				}
			],
			"restarts": [
			]
		}
	]
}}
